Workbook

Sheet Sheet1
A1: Host | B1: Group | C1: Name | D1: Asset tag | F1: class
A2: TUV_Batsumber_Sugnugur_Unitel | B2: All_sites, Tuv, zte_rectifiers | C2: TUV_Batsumber_Sugnugur_Unitel | D2: 260302-260313- 165330/1 | E2: =VLOOKUP(D2,Sheet2!E:Q,13,FALSE) -> C | F2: C
A3: UVS.Hovd_ShiverBag_TungetiinOroiUul_MP25 | B3: All_sites, Solar, Uvs, solar_huawei | C3: UVS_Hovd_ShiverBag_TungetiinOroiUul | D3: 11-T-85-00078 | E3: =VLOOKUP(D3,Sheet2!E:Q,13,FALSE) -> D | F3: D
A4: UVS.Ulaangom_HarhiraaHotel_MP25 | B4: All_sites, Rect_HUAWEI_SMU02B, Uvs | C4: UVS_Ulaangom_HarhiraaHotel | D4: 11-T-85-00077 | E4: =VLOOKUP(D4,Sheet2!E:Q,13,FALSE) -> C | F4: C
A5: UVS.Tarialan_TeeliinSuurin_MP25 | B5: All_sites, Solar, Uvs, solar_huawei | C5: UVS_Tarialan_TeeliinSuurin | D5: 11-T-85-00076 | E5: =VLOOKUP(D5,Sheet2!E:Q,13,FALSE) -> D | F5: D
A6: UVS.Naranbulag_ZostiinHutul_MP25 | B6: All_sites, Solar, Uvs, solar_huawei | C6: UVS_Naranbulag_ZostiinHutul | D6: 11-T-85-00075 | E6: =VLOOKUP(D6,Sheet2!E:Q,13,FALSE) -> D | F6: D
A7: UVS.Zuungovi_UguumurBag_IhUlaanUul_MP24 | B7: All_sites, Solar, Uvs, solar_huawei | C7: UVS_Zuungovi_UguumurBag_IhUlaanUul | D7: 11-T-85-00073 | E7: =VLOOKUP(D7,Sheet2!E:Q,13,FALSE) -> D | F7: D
A8: UVS.Ulaangom_9bag_Buyant27_25aToot_MP24 | B8: All_sites, Rect_HUAWEI_SMU02B, Uvs | C8: UVS_Ulaangom_9bag_Buyant27-25aToot | D8: 11-T-85-00072 | E8: =VLOOKUP(D8,Sheet2!E:Q,13,FALSE) -> C | F8: C
A9: UVS.Ulaangom_Airport_MP24 | B9: All_sites, Rect_HUAWEI_SMU02B, Uvs, ameter | C9: UVS_Ulaangom_Airport | D9: 11-T-85-00069 | E9: =VLOOKUP(D9,Sheet2!E:Q,13,FALSE) -> C | F9: C
A10: UVS.Ulaangom_5bag_UlaanUul | B10: All_sites, Rect_HUAWEI_SMU02B, Uvs, ameter | C10: UVS_Ulaangom_5bag_UlaanUul | D10: 11-T-85-00068 | E10: =VLOOKUP(D10,Sheet2!E:Q,13,FALSE) -> C | F10: C
A11: UVS.Ulaangom_Nomin_NMD110 | B11: All_sites, Uvs, ZTE_YDN | C11: UVS_Ulaangom_Nomin | D11: 11-T-85-00067 | E11: =VLOOKUP(D11,Sheet2!E:Q,13,FALSE) -> B | F11: B
A12: UVS.Umnugovi_UliastBag | B12: All_sites, Solar, Uvs | C12: UVS_Umnugovi_UliastBag | D12: 11-T-85-00066 | E12: =VLOOKUP(D12,Sheet2!E:Q,13,FALSE) -> F | F12: F
A13: UVS.Tes_SharsuuriBoomt | B13: All_sites, Rect_HUAWEI_SMU02B, Uvs, ameter | C13: UVS_Tes_SharSuuriBoomt | D13: 11-T-85-00064 | E13: =VLOOKUP(D13,Sheet2!E:Q,13,FALSE) -> D | F13: D
... A1657: CHD._16xor_Khailaast_DU_LLC_NMD30_ULN | B1657: All_sites, ULN_Chingelgei_duureg, Ulaanbaatar | C1657: ULN_CHD_16hor_Hailaast_D&U_LLC | D1657: 11-T-15-00095 | E1657: =VLOOKUP(D1657,Sheet2!E:Q,13,FALSE) -> B | F1657: B
A1658: DC.TCB.rsu | B1658: All_sites, DC, DC_Status | C1658: TCB-1 | D1658: 11-T-15-00053 | E1658: =VLOOKUP(D1658,Sheet2!E:Q,13,FALSE) -> #N/A | F1658: #N/A
A1659: CHD.CrownCenter_ISS100_ULN | B1659: 1Phase, All_sites, ULN_Chingelgei_duureg, Ulaanbaatar | C1659: ULN_CHD_CrownCenter | D1659: 11-T-15-00043 | E1659: =VLOOKUP(D1659,Sheet2!E:Q,13,FALSE) -> C | F1659: C
A1660: CHD._19hor_GuntiinAmniiEhHoidUul_ULN | B1660: All_sites, ULN_Chingelgei_duureg, Ulaanbaatar | C1660: ULN_CHD_19hor_GuntiinAmniiEhHoidUul | D1660: 11-T-15-00041 | E1660: =VLOOKUP(D1660,Sheet2!E:Q,13,FALSE) -> C | F1660: C
A1661: CHD._4hor_TSEG_MShUTuv_ISS100_ULN | B1661: All_sites, Rect_HUAWEI_SMU02B, ULN_Chingelgei_duureg, Ulaanbaatar | C1661: ULN_CHD_4hor_TSEG_MShUTuv | D1661: 11-T-15-00039 | E1661: =VLOOKUP(D1661,Sheet2!E:Q,13,FALSE) -> B | F1661: B
A1662: CHD.JigjidZuslan_ISS100_ULN | B1662: All_sites, ULN_Chingelgei_duureg, Ulaanbaatar | C1662: ULN_CHD_JigjidZuslan | D1662: 11-T-15-00038 | E1662: =VLOOKUP(D1662,Sheet2!E:Q,13,FALSE) -> D | F1662: D
A1663: CHD._2hor_OronZai_NMD110_ULN | B1663: All_sites, Rect_HUAWEI_SMU02B, ULN_Chingelgei_duureg, Ulaanbaatar | C1663: ULN_CHD_2hor_OronZai | D1663: 11-T-15-00037 | E1663: =VLOOKUP(D1663,Sheet2!E:Q,13,FALSE) -> B | F1663: B
A1664: CHD._6HOR_9bair_NMD_ULN | B1664: All_sites, ULN_Chingelgei_duureg, Ulaanbaatar | C1664: ULN_CHD_6hor_9Bair | D1664: 11-T-15-00035 | E1664: =VLOOKUP(D1664,Sheet2!E:Q,13,FALSE) -> B | F1664: B
A1665: CHD._18hor_Shadivlan_ULN | B1665: All_sites, ULN_Chingelgei_duureg, Ulaanbaatar, ZTE_YDN | C1665: ULN_CHD_18hor_Shadivlan | D1665: 11-T-15-00032 | E1665: =VLOOKUP(D1665,Sheet2!E:Q,13,FALSE) -> B | F1665: B
A1666: CHD._6xor_58Bair_NMD30_ULN | B1666: All_sites, ULN_Chingelgei_duureg, Ulaanbaatar, ZTE_YDN | C1666: ULN_CHD_6hor_58Bair | D1666: 11-T-15-00031 | E1666: =VLOOKUP(D1666,Sheet2!E:Q,13,FALSE) -> B | F1666: B
A1667: CHD._3hor_PeaceTower_ISS100_ULN | B1667: 1Phase, All_sites, Rect_HUAWEI_SMU02B, ULN_Chingelgei_duureg, Ulaanbaatar | C1667: ULN_CHD_3hor_PeaceTower | D1667: 11-T-15-00028 | E1667: =VLOOKUP(D1667,Sheet2!E:Q,13,FALSE) -> C | F1667: C
A1668: CHD._1hor_TDBTuulSalbar_ISS100_ULN | B1668: All_sites, Rect_HUAWEI_SMU02B, ULN_Chingelgei_duureg, Ulaanbaatar | C1668: ULN_CHD_1hor_TDBTuulSalbar | D1668: 11-T-15-00025 | E1668: =VLOOKUP(D1668,Sheet2!E:Q,13,FALSE) -> C | F1668: C
A1669: CHD._3hor_MongolNews_MOS42_ULN | B1669: 1Phase, All_sites, ULN_Chingelgei_duureg, Ulaanbaatar | C1669: ULN_CHD_3hor_MongolNews | D1669: 11-T-15-00024 | E1669: =VLOOKUP(D1669,Sheet2!E:Q,13,FALSE) -> B | F1669: B
A1670: CHD._15hor_Hailaast_Unitel_ISS100_ULN | B1670: All_sites, Rect_HUAWEI_SMU02B, ULN_Chingelgei_duureg, Ulaanbaatar | C1670: ULN_CHD_15hor_Hailaast_Unitel | D1670: 11-T-15-00023 | E1670: =VLOOKUP(D1670,Sheet2!E:Q,13,FALSE) -> B | F1670: B
... A1986: BND.MW204_ULN | B1986: All_sites, ULN_Baganuur_duureg, Ulaanbaatar | C1986: ULN_BND_MW204 | D1986: 11-T-10-00001 | E1986: =VLOOKUP(D1986,Sheet2!E:Q,13,FALSE) -> C | F1986: C

Sheet Sheet2
A1: № | B1: id | C1: Ажлын төлөв | D1: Ажлын тоо | E1: Код | F1: Сайт | G1: Үл тохирол | H1: Тайлагнасан огноо | I1: Төлөв | J1: Байршил/Аймаг/Хот | K1: Байршил/Сум/Дүүрэг | L1: Байршил/Баг/Хороо | M1: Байршил/Байршил | N1: Бусад мэдээлэл/Бүсчлэл | O1: Бусад мэдээлэл/Харьяалал | P1: Бусад мэдээлэл/Ассан огноо | Q1: Бусад мэдээлэл/Зэрэглэл | R1: Cellname/2g | S1: Cellname/3g | T1: Cellname/4g | U1: Cellname/5g | V1: Бусад мэдээлэл/Хариуцагч | W1: Хэрэглэгч | X1: URL | Y1: Бусад мэдээлэл/Эзэмшигч | Z1: checkKeyId | AA1: what3words | AB1: latLongCoordinate
A2: 1 | B2: 17485587875672 | C2: Асаахад бэлдэж байна | E2: 260401-260402- 163809/1 | F2: Нэр олгоогүй | G2: 0 | I2: Асаахад бэлдэж байна | J2: Хөвсгөл | K2: Мөрөн | L2: 1-р баг | W2: tsamba | X2: https://sm.mobicom.mn/mdobject/dataview/1525387912476&dv[id][]=17485587875672
A3: 2 | B3: 17485583430642 | C3: Байгуулж байна | D3: 18 | E3: 11-T-83-00080 | F3: BAU_Ulgii_13Bag_KazakhstanDelguur | G3: 0 | I3: Шийдэл тодорхойлж байна | J3: Баян-Өлгий | K3: Өлгий | L3: 13-р баг, Жана ауыл | M3: Баян-Өлгий аймаг Өлгий сум 13-р баг Казакстандэлгүүр | N3: Аймгийн төв | O3: ROC_URC_BAU | Q3: B | T3: BAU_S4_Tuv13BagKazahkstanDelguur-1 BAU_S4_Tuv13BagKazahkstanDelguur-2 BAU_S4_Tuv13BagKazahkstanDelguur-3 BAU_S4_Tuv13BagKazahkstanDelguur_B7-1 BAU_S4_Tuv13BagKazahkstanDelguur_B7-2 BAU_S4_Tuv13BagKazahkstanDelguur_B7-3 BAU_S4_Tuv13BagKazahkstanDelguur_B1-1 BAU_S4_Tuv13BagKazahkstanDelguur_B1-2 BAU_S4_Tuv13BagKazahkstanDelguur_B1-3 | V3: Mobicom | W3: battulga | X3: https://sm.mobicom.mn/mdobject/dataview/1525387912476&dv[id][]=17485583430642 | Y3: Бусад | Z3: 17485583430642 | AB3: 89.961777777777783172|48.963558333333338624
A4: 3 | B4: 17485571456372 | C4: Байгуулж байна | D4: 7 | E4: 11-T-15-00185 | F4: ULN_CHD_5hor_GeserSum_RFID_Sector | G4: 0 | I4: Хэрэгжилтд шилжүүлж байна | J4: Улаанбаатар | K4: Чингэлтэй | L4: 5-р хороо | M4: Улаанбаатар хот Чингэлтэй дүүрэг 5-р хороо Гэсэр сүмийн урд гэрлийн шон дээр | N4: Улаанбаатар | O4: ID_Planning | P4: 46112 | Q4: F | T4: UB_H4_sCHD5horGeserSumLightPole-1 (UB_Gandan) UB_H4_sCHD5horGeserSumLightPole-2(UB_Gandan) | W4: sergelen.u | X4: https://sm.mobicom.mn/mdobject/dataview/1525387912476&dv[id][]=17485571456372 | Y4: Бусад | Z4: 17485571456372 | AB4: 47.91674471367652,106.9163167476654
A5: 4 | B5: 17485571456302 | C5: Байгуулж байна | D5: 8 | E5: 11-T-46-00181 | F5: UMG_Dalanzadgad_8Bag_DZApartment_9Bair | G5: 0 | I5: СДБ-н ажил гүйцэтгэж байна | J5: Өмнөговь | K5: Даланзадгад | M5: Өмнөговь аймаг Даланзадгад хот Даланзадгад апартмент 9-р байрны дээвэрт | N5: Аймгийн төв | O5: ROC_GRC_UMG | P5: 46111 | Q5: B | S5: UMG_A3_Tuv8BagDZApartment-1 UMG_A3_Tuv8BagDZApartment-2 UMG_A3_Tuv8BagDZApartment-3 | T5: UMG_H4_Tuv8BagDZApartment-1 UMG_H4_Tuv8BagDZApartment-2 UMG_H4_Tuv8BagDZApartment-3 UMG_H4_Tuv8BagDZApartment_B7-1 UMG_H4_Tuv8BagDZApartment_B7-2 UMG_H4_Tuv8BagDZApartment_B7-3 UMG_H4_Tuv8BagDZApartment_B28-2 UMG_H4_Tuv8BagDZApartment_B28-3 | W5: sergelen.u | X5: https://sm.mobicom.mn/mdobject/dataview/1525387912476&dv[id][]=17485571456302 | Y5: Мобиком | Z5: 17485571456302 | AB5: 43.572809,104.434485
A6: 5 | B6: 17485570967712 | C6: Хэвийн | D6: 9 | E6: 11-T-67-00101 | F6: Huv_Murun_8Bag_DalaiVanSurguuli | G6: 0 | I6: Хэвийн | J6: Хөвсгөл | K6: Мөрөн | L6: 8-р баг | M6: Хөвсгөл аймаг Мөрөн хот, 8-р баг, ДалайВан сургуулийн 3давхарт. | N6: Аймгийн төв | O6: ROC_ERC_HUV | P6: 46106 | Q6: B | T6: HUV_H4_Tuv8BagDalaiVanSurguuli-1 HUV_H4_Tuv8BagDalaiVanSurguuli-2 HUV_H4_Tuv8BagDalaiVanSurguuli-3 | W6: ankhbayar.g | X6: https://sm.mobicom.mn/mdobject/dataview/1525387912476&dv[id][]=17485570967712 | Y6: Мобиком | Z6: 17485570967712 | AB6: 49.629971,100.159474
A7: 6 | B7: 17485552214692 | C7: Хэвийн | D7: 11 | E7: 11-T-17-00217 | F7: ULN_HUD_8hor_TashgaiAguulah | G7: 0 | H7: 46094.376 | I7: Хэвийн | J7: Улаанбаатар | K7: Хан-Уул | L7: 8-р хороо | N7: Улаанбаатар | W7: tuguldur.enkh | X7: https://sm.mobicom.mn/mdobject/dataview/1525387912476&dv[id][]=17485552214692 | Z7: 17485552214692 | AB7: 47.83904660507439,106.79110769000393
A8: 7 | B8: 17485552157112 | C8: Хэвийн | D8: 13 | E8: 11-T-17-00295 | F8: ULN_HUD_8hor_TCB2_SolarPowerPlant | G8: 0 | H8: 46093.124 | I8: Хэвийн | J8: Улаанбаатар | K8: Хан-Уул | L8: 8-р хороо | N8: Улаанбаатар | W8: tuguldur.enkh | X8: https://sm.mobicom.mn/mdobject/dataview/1525387912476&dv[id][]=17485552157112 | Z8: 17485552157112 | AB8: 47.838909220010024,106.79058624046513
A9: 8 | B9: 17485542104942 | C9: Хэвийн | D9: 46 | E9: 16-T-13-00252 | F9: ULN_BZD_3hor_MojoKaraoke_Femto | G9: 0 | I9: Хэвийн | J9: Улаанбаатар | K9: Баянзүрх | L9: 3-р хороо | M9: Сансрын тунел &quot;Можо кареоке&quot; B1 давхарт | N9: Улаанбаатар | O9: RAND_RDOD | P9: 46086 | Q9: F | T9: UB_B4_Femto_MojoKareoke-1 | V9: мобиком | W9: Sainjargal | X9: https://sm.mobicom.mn/mdobject/dataview/1525387912476&dv[id][]=17485542104942 | Y9: Мобиком | Z9: 17485542104942 | AB9: 47.91674471367652,106.9163167476654
A10: 9 | B10: 17485539545732 | C10: Байгуулж байна | D10: 5 | E10: 260305-260405- 075123/2 | F10: Нэр олгоогүй | G10: 0 | I10: Ашиглалтанд шилжүүлж байна | J10: Завхан | K10: Тосонцэнгэл | L10: 6-р баг, Идэр | W10: sergelen.u | X10: https://sm.mobicom.mn/mdobject/dataview/1525387912476&dv[id][]=17485539545732
A11: 10 | B11: 17485539545662 | C11: Байгуулж байна | D11: 5 | E11: 260305-260405- 075123/1 | F11: Нэр олгоогүй | G11: 0 | I11: Ашиглалтанд шилжүүлж байна | J11: Увс | K11: Тэс | L11: 1-р баг | W11: sergelen.u | X11: https://sm.mobicom.mn/mdobject/dataview/1525387912476&dv[id][]=17485539545662
A12: 11 | B12: 17485536693922 | C12: Байгуулж байна | D12: 14 | E12: 11-T-46-00180 | F12: UMG_Dalanzadgad_6Bag_Niseh2-203A2block | G12: 0 | I12: Хэрэгжилтд шилжүүлж байна | J12: Өмнөговь | K12: Даланзадгад | L12: хануул | M12: Өмнөговь аймаг, Даланзадгад сум, Их уулын 6-р баг, Нисэх 2-203А/2 | N12: Аймгийн төв | Q12: B | W12: nasanjargal.g | X12: https://sm.mobicom.mn/mdobject/dataview/1525387912476&dv[id][]=17485536693922 | Z12: 17485536693922 | AB12: 43.572809,104.434485
A13: 12 | B13: 17485536688452 | C13: Байгуулж байна | D13: 16 | E13: 251201-260601- 164200/1 | F13: Нэр олгоогүй | G13: 0 | I13: Ашиглалтанд шилжүүлж байна | J13: Өмнөговь | K13: Даланзадгад | L13: Далан | W13: nasanjargal.g | X13: https://sm.mobicom.mn/mdobject/dataview/1525387912476&dv[id][]=17485536688452
A14: 13 | B14: 17485534896532 | C14: Хэвийн | D14: 5 | E14: 260302-260313- 165330/1 | F14: TUV_Batsumber_Sugnugur_Unitel | G14: 0 | I14: Хэвийн | J14: Төв | K14: Батсүмбэр | L14: 3-р баг, Баянгол | M14: Төв аймаг, Батсүмбэр сум, Сөгнөгөр 3-р баг, айлын хашаанд, Юнителийн сайт дотор | N14: Орон нутаг | O14: ID_Planning | P14: 46092 | Q14: C | T14: TUV_B4_BatsumberSugnugurUnitel1-1 TUV_B4_BatsumberSugnugurUnitel2-1 | V14: Юнитель ХХК -ны харуул хариуцна. | W14: ankhbayar.g | X14: https://sm.mobicom.mn/mdobject/dataview/1525387912476&dv[id][]=17485534896532 | Y14: Юнител | Z14: 17485534896532 | AB14: 48.391482,106.854723
A15: 14 | B15: 17485534744212 | C15: Хэвийн | D15: 45 | E15: 11-T-15-00184 | F15: ULN_CHD_1hor_CapitalCenter_1301_Femto | G15: 0 | I15: Хэвийн | J15: Улаанбаатар | K15: Чингэлтэй | L15: 1-р хороо | M15: Улаанбаатар хот Чингэлтэй дүүрэг 1-р хороо Capital center 13давхар | N15: Улаанбаатар | O15: RAND_RDOD | P15: 46085 | Q15: F | T15: UB_B4_Femto_Capitalcenter | W15: tsamba | X15: https://sm.mobicom.mn/mdobject/dataview/1525387912476&dv[id][]=17485534744212 | Y15: Бусад | Z15: 17485534744212 | AB15: 47.91879,106.901936
A16: 15 | B16: 17485511881512 | C16: Байгуулж байна | D16: 17 | E16: 11-T-41-00145 | F16: TUV_Lun_AltganaResource | G16: 0 | I16: СДБ-н ажил гүйцэтгэж байна | J16: Төв | K16: Лүн | L16: 2-р баг, Өгөөмөр | M16: Төв аймаг Лүн сум Алтгана ресурс | N16: Орон нутаг | Q16: D | W16: nasanjargal.g | X16: https://sm.mobicom.mn/mdobject/dataview/1525387912476&dv[id][]=17485511881512 | Z16: 17485511881512 | AB16: 47.979674,104.975055
A17: 16 | B17: 17485505708212 | C17: Хэвийн | D17: 7 | E17: 11-T-21-00082 | F17: DOR_Herlen_5bag_Diviz_Netcom | G17: 0 | H17: 46107.105 | I17: Хэвийн | J17: Дорнод | K17: Хэрлэн | L17: 5-р баг | M17: Дорнод аймгийн төв Хэрлэн сумын 5-р баг, Неткомын байр цамхагтай сайт | N17: Аймгийн төв | O17: ROC_URC_DOR | Q17: C | T17: DOR_B4_Herlen5bagNetcom_B8-1 DOR_B4_Herlen5bagNetcom_B8-2 DOR_B4_Herlen5bagNetcom_B8-3 | W17: erdenetsogt | X17: https://sm.mobicom.mn/mdobject/dataview/1525387912476&dv[id][]=17485505708212 | Y17: МХС | Z17: 17485505708212 | AB17: 48.062758,114.6365
A18: 17 | B18: 17485502307992 | C18: Хэвийн | D18: 44 | E18: 11-T-17-00303 | F18: ULN_HUD_17hor_IhMongolPlaza_Femto | G18: 0 | I18: Хэвийн | J18: Улаанбаатар | K18: Хан-Уул | L18: 18-р хороо | M18: ХУД, 17-р хороо, Ихмонгол плаза дотор байрлах &quot;Хаан банк&quot; | N18: Улаанбаатар | O18: ID_System | P18: 46063 | Q18: F | T18: UB_B4_IhMongolPlaza-1 | W18: Sainjargal | X18: https://sm.mobicom.mn/mdobject/dataview/1525387912476&dv[id][]=17485502307992 | Y18: Мобиком | Z18: 17485502307992 | AB18: 47.91674471367652,106.9163167476654
A19: 18 | B19: 17485501597932 | C19: Байгуулж байна | D19: 13 | E19: 11-T-16-00162 | F19: ULN_BGD_20hor_Bars2_Femto | G19: 0 | I19: Хэрэгжилтд шилжүүлж байна | J19: Улаанбаатар | K19: Баянгол | L19: 21-р хороо | M19: Барс-2 худалдааны төв | N19: Улаанбаатар | O19: ID_Planning | P19: 46099 | Q19: F | T19: UB_B4_Femto_iBGD20horBars2-1 UB_B4_Femto_iBGD20horBars2-2 | V19: bars2 zah | W19: battulga | X19: https://sm.mobicom.mn/mdobject/dataview/1525387912476&dv[id][]=17485501597932 | Y19: Бусад | Z19: 17485501597932 | AB19: 106.83166111111110297|47.910044444444444878
A20: 19 | B20: 17485492935012 | C20: Байгуулж байна | D20: 7 | E20: 11-T-17-00302 | F20: ULN_HUD_22hor_KunzSurguuli | G20: 0 | I20: Хэрэгжилтд шилжүүлж байна | J20: Улаанбаатар | K20: Хан-Уул | L20: 22-р хороо | M20: Улаанбаатар хот Хан Уул дүүрэг 22-р хороо Күнз сургуулийн дээвэр дээр минишелтер байрлуулсан | N20: Улаанбаатар | O20: ID_Planning | P20: 46079 | Q20: B | T20: UB_H4_HUD22horKunzSurguuli-1 UB_H4_HUD22horKunzSurguuli-2 UB_H4_HUD22horKunzSurguuli-3 | W20: sergelen.u | X20: https://sm.mobicom.mn/mdobject/dataview/1525387912476&dv[id][]=17485492935012 | Y20: Мобиком | Z20: 17485492935012 | AB20: 47.871562859556725,106.90519022139105
A21: 20 | B21: 17485481032202 | C21: Байгуулж байна | D21: 44 | E21: 11-T-17-00304 16-T-17-00304 | F21: ULN_HUD_6hor_KhanBankDataCenter_Femto | G21: 0 | I21: Хэрэгжилтд шилжүүлж байна | J21: Улаанбаатар | K21: Хан-Уул | L21: 6-р хороо | M21: ХУД, 6-р хороо, &quot;Хаан банк дата центр&quot; | N21: Улаанбаатар | O21: ID_System | P21: 46014 | Q21: F | T21: UB_B4_Femto_DataHall-1 | W21: Sainjargal | X21: https://sm.mobicom.mn/mdobject/dataview/1525387912476&dv[id][]=17485481032202 | Y21: Мобиком | Z21: 17485481032202 | AB21: 47.8429830242326,106.7966526
A22: 21 | B22: 17485446416552 | C22: Байгуулж байна | D22: 6 | E22: 11-T-62-00085 | F22: UVH_Nariinteel_ArtsBag_Indert | G22: 0 | I22: Хэрэгжилтд шилжүүлж байна | J22: Өвөрхангай | K22: Нарийнтээл | L22: Арц баг | M22: Өвөрхангай аймагНарийнтээл сум Арц баг Индэрт | N22: Орон нутаг | O22: ROC_URC_UVH | Q22: D | W22: erdenetsogt | X22: https://sm.mobicom.mn/mdobject/dataview/1525387912476&dv[id][]=17485446416552 | Y22: Мобиком | Z22: 17485446416552 | AB22: 46.034604,101.353135
A23: 22 | B23: 17485431678702 | C23: Байгуулж байна | D23: 44 | E23: 11-T-17-00293 | F23: ULN_HUD_15hor_TavanBogdMachinery_Femto | G23: 0 | I23: Хэрэгжилтд шилжүүлж байна | J23: Улаанбаатар | K23: Хан-Уул | L23: 15-р хороо | M23: УБ хот Хан уул дүүрэг 15-р хороо Tavanbogd Machinery | N23: Улаанбаатар | O23: ID_System | P23: 45649 | Q23: F | T23: UB_B4_Femto_Tavanbogdmachinery | V23: IT-99023371 | W23: Sainjargal | X23: https://sm.mobicom.mn/mdobject/dataview/1525387912476&dv[id][]=17485431678702 | Z23: 17485431678702 | AB23: 47.91674471367652,106.9163167476654
A24: 23 | B24: 17485431511712 | C24: Байгуулж байна | D24: 44 | E24: 11-T-44-00089 | F24: DOG_Hatanbulag_HiliinTsergiin0169Angi_Bo | G24: 0 | I24: Хэрэгжилтд шилжүүлж байна | J24: Дорноговь | K24: Эрдэнэ | L24: 1-р баг, Бүрдэнэ | M24: Хилийн цэргийн 0169 дүгээр анги | N24: Орон нутаг | O24: ROC_GRC_DOG | P24: 45506 | Q24: D | T24: DOG_B4_Femto_Erdene_Zastav-4_UzuurUs DOG_B4_Femto_Erdene_Zastav-1_ElsenDaravgai DOG_B4_Femto_Erdene_Zastav-3 DOG_B4_Femto_Erdene_Zastav-6 DOG_B4_Femto_Erdene_Zastav-8 DOG_B4_Femto_Erdene_Zastav-9 | W24: Sainjargal | X24: https://sm.mobicom.mn/mdobject/dataview/1525387912476&dv[id][]=17485431511712 | Y24: Мобиком | Z24: 17485431511712 | AB24: 44.4446897521094,111.091169415635
A25: 24 | B25: 17485423795612 | C25: Хэвийн | D25: 19 | E25: 11-T-83-00077 | F25: BAU_Buyant_2Bag_UlaanHutliinOroi | G25: 0 | I25: Хэвийн | J25: Баян-Өлгий | K25: Буянт | L25: 2-р баг, Хөлцөөт | M25: Баян-Өлгий аймаг Буянт сум 2-р баг Хөлцөөт баг Улаан хөтлийн орой | N25: Орон нутаг | O25: ROC_URC_BAU | P25: 46022 | Q25: F | T25: BAU_H4_Buyant2BagUlaanHutliinOroi_B8-1 BAU_H4_Buyant2BagUlaanHutliinOroi_B8-2 | V25: Mobicom | W25: battulga | X25: https://sm.mobicom.mn/mdobject/dataview/1525387912476&dv[id][]=17485423795612 | Y25: МХС | Z25: 17485423795612 | AB25: 89.627883333333329574|48.563288888888884287
A26: 25 | B26: 17485423559292 | C26: Хэвийн | D26: 17 | E26: 11-T-82-00070 | F26: GOA_Esunbulag_NaranbulagBag_HanAltai | G26: 0 | H26: 46105.036 | I26: Хэвийн | J26: Говь-Алтай | K26: Есөнбулаг | L26: 3-р баг, Жаргалант | M26: Говь-Алтай аймаг, Есөнбулаг сум, Наранбулаг баг, Хан Алтай ресорс, Амралтын байр | N26: Орон нутаг | O26: ROC_URC_GOA | P26: 46014 | Q26: D | T26: GOA_H4_EsunbulagNaranbulagBagHanAltai-1 GOA_H4_EsunbulagNaranbulagBagHanAltai-2 GOA_H4_EsunbulagNaranbulagBagHanAltai-3 | V26: Mobicom | W26: battulga | X26: https://sm.mobicom.mn/mdobject/dataview/1525387912476&dv[id][]=17485423559292 | Y26: Мобиком | Z26: 17485423559292 | AB26: 96.869222222222219898|46.069700000000004536
A27: 26 | B27: 17485422147402 | C27: Байгуулж байна | D27: 11 | E27: 11-T-17-00297 | F27: ULN_HUD_15hor_TusgaltOffice | G27: 0 | I27: Хэрэгжилтд шилжүүлж байна | J27: Улаанбаатар | K27: Хан-Уул | L27: 15-р хороо | M27: Улаанбаатар хот Хан-Уул дүүрэг 15-р хороо Тусгалт оффис | N27: Улаанбаатар | O27: ID_Planning | P27: 46015 | Q27: B | T27: UB_H4_HUD15horTusgaltOffice-1 UB_H4_HUD15horTusgaltOffice-2 UB_H4_HUD15horTusgaltOffice-3 UB_H4_HUD15horTusgaltOffice_B7-1 UB_H4_HUD15horTusgaltOffice_B7-3 UB_H4_HUD15horTusgaltOffice_B28-1 | U27: UB_H5_HUD15horTusgaltOffice-1 UB_H5_HUD15horTusgaltOffice-2 UB_H5_HUD15horTusgaltOffice-3 | W27: nasanjargal.g | X27: https://sm.mobicom.mn/mdobject/dataview/1525387912476&dv[id][]=17485422147402 | Y27: Мобиком | Z27: 17485422147402 | AB27: 47.908014624687354,106.92314028739929
A28: 27 | B28: 17485421926612 | C28: Байгуулж байна | D28: 17 | E28: 11-T-48-00051 | F28: DUG_Saintsagaan_Uizenbag_HongoriinUul | G28: 0 | I28: Угсралт хийгдэж байна | J28: Дундговь | K28: Сайнцагаан | L28: 4-р баг, Үйзэн | M28: Дундговь аймаг Сайнцагаан сум 4-р баг Үйзэн баг Хонгорын уул | N28: Орон нутаг | O28: ROC_GRC_DUG | P28: 46022 | Q28: F | R28: DUG_H2_SaintsagaanUizenBag-1 DUG_H2_SaintsagaanUizenBag-2 | T28: DUG_H4_SaintsagaanUizenBag_B8-1 DUG_H4_SaintsagaanUizenBag_B8-2 | W28: nasanjargal.g | X28: https://sm.mobicom.mn/mdobject/dataview/1525387912476&dv[id][]=17485421926612 | Y28: Мобиком | Z28: 17485421926612 | AB28: 45.496324,106.445328
A29: 28 | B29: 17485419051382 | C29: Байгуулж байна | D29: 44 | E29: 11-T-21-0007 | F29: DOR_Herlen_1bag_DornodGuril_Femto | G29: 0 | I29: Хэрэгжилтд шилжүүлж байна | J29: Дорнод | K29: Хэрлэн | L29: 1-р баг | M29: Дорнод аймаг, Чойбалсан хот, 1-р баг Дорнод гурил ххк | N29: Орон нутаг | O29: ROC_URC_DOR | P29: 45821 | Q29: F | T29: DOR_B4_Femto_Guril-1 DOR_B4_Femto_Guril-2 DOR_B4_Femto_Guril-3 | W29: Sainjargal | X29: https://sm.mobicom.mn/mdobject/dataview/1525387912476&dv[id][]=17485419051382 | Y29: Мобиком | Z29: 17485419051382 | AB29: 47.91674471367652,106.9163167476654
A30: 29 | B30: 17485419027682 | C30: Байгуулж байна | D30: 44 | E30: 11-T-44-00091 | F30: DOG_Erdene_HiliinTsergiin0129Angi_Femto | G30: 0 | I30: Хэрэгжилтд шилжүүлж байна | J30: Дорноговь | K30: Эрдэнэ | L30: 3-р баг, Цагаан хөтөл | M30: Дорноговь аймаг, Эрдэнэ сум Хилийн цэргийн 0129 дүгээр анги | N30: Орон нутаг | O30: ROC_GRC_DOG | P30: 45654 | Q30: D | W30: Sainjargal | X30: https://sm.mobicom.mn/mdobject/dataview/1525387912476&dv[id][]=17485419027682 | Y30: Мобиком | Z30: 17485419027682 | AB30: 47.91674471367652,106.9163167476654
A31: 30 | B31: 17485419006062 | C31: Байгуулж байна | D31: 44 | E31: 11-T-41-00144 | F31: TUV_Bayan_Buuruljuut_Femto | G31: 0 | I31: Хэрэгжилтд шилжүүлж байна | J31: Төв | K31: Баян | L31: 2-р баг, Өгөөмөр | M31: Төв аймаг Баян сум Бөөрөлжүүт | N31: Улаанбаатар | O31: ID_System | P31: 45649 | Q31: F | T31: TUV_B4_Femto_Buuruljuut_1Floor TUV_B4_Femto_Buuruljuut_2Floor | W31: Sainjargal | X31: https://sm.mobicom.mn/mdobject/dataview/1525387912476&dv[id][]=17485419006062 | Z31: 17485419006062 | AB31: 47.2416656722207,107.802937079663
A32: 31 | B32: 17485418978462 | C32: Байгуулж байна | D32: 44 | E32: 11-T-14-00274 | F32: ULN_SBD_1hor_ICTGroup_Femto | G32: 0 | I32: Хэрэгжилтд шилжүүлж байна | J32: Улаанбаатар | K32: Хан-Уул | L32: 15-р хороо | M32: Улаанбаатар хот ,Сүхбаатар дүүрэг ,1-р хороо, Ай си ти групп | N32: Улаанбаатар | O32: ID_System | P32: 45506 | Q32: F | T32: UB_B4_Femto_ICTgroup_office-1 | W32: Sainjargal | X32: https://sm.mobicom.mn/mdobject/dataview/1525387912476&dv[id][]=17485418978462 | Y32: Мобиком | Z32: 17485418978462 | AB32: 47.9130646360479,106.927054973409
A33: 32 | B33: 17485418924162 | C33: Байгуулж байна | D33: 44 | E33: 11-T-61-00106 | F33: ORH_BayanUndur_ZesErdeneOffice_Femto | G33: 0 | I33: Шийдэл тодорхойлж байна | J33: Орхон | K33: Баян-Өндөр | L33: 3-р баг, Уурхайчин | M33: Орхон аймаг Баянөндөр сум 3-р микро Зэс эрдэнэ оффис | N33: Орон нутаг | O33: ROC_ERC | P33: 45821 | Q33: F | T33: ORH_B4_Femto_ZeserdeneOFfice | W33: Sainjargal | X33: https://sm.mobicom.mn/mdobject/dataview/1525387912476&dv[id][]=17485418924162 | Y33: Мобиком | Z33: 17485418924162 | AB33: 104.05652999999999508|49.026159999999997297
A34: 33 | B34: 17485418401552 | C34: Байгуулж байна | D34: 44 | E34: 11-T-21-00078 | F34: DOR_Halhgol_SumberBoomt_Femto | G34: 0 | I34: Шийдэл тодорхойлж байна | J34: Дорнод | K34: Халхгол | L34: 1-р баг, Сүмбэр | M34: Дорнод аймаг Халх гол сум Сүмбэр боомт | N34: Орон нутаг | O34: ROC_URC_DOR | P34: 45649 | Q34: F | T34: DOR_B4_Femto_Sumberboomt-1 DOR_B4_Femto_Sumberboomt-2 | V34: Холбооны дарга: Энхжаргал 89110665 | W34: Sainjargal | X34: https://sm.mobicom.mn/mdobject/dataview/1525387912476&dv[id][]=17485418401552 | Y34: Мобиком | Z34: 17485418401552 | AB34: 47.91674471367652,106.9163167476654
A35: 34 | B35: 17485418360672 | C35: Байгуулж байна | D35: 44 | E35: 11-T-21-00079 | F35: DOR_Halhgol_ZadgaitBoomt_Femto | G35: 0 | I35: Хайгуул хийгдэж байгаа | J35: Дорнод | K35: Халхгол | L35: 1-р баг, Сүмбэр | M35: Дорнод Халхгол сум Задгайт боомт | N35: Орон нутаг | O35: ROC_URC_DOR | P35: 45634 | Q35: F | T35: DOR_B4_Femto_ZadgaitZastav DOR_B4_Femto_ZadgaitZastav-2 | V35: Холбооны дарга: Энхжаргал 89110665 | W35: Sainjargal | X35: https://sm.mobicom.mn/mdobject/dataview/1525387912476&dv[id][]=17485418360672 | Y35: Мобиком | Z35: 17485418360672 | AB35: 46.8271336665276,118.71954925427019
A36: 35 | B36: 17485411760722 | C36: Байгуулж байна | D36: 17 | E36: 11-T-82-00071 | F36: GOA_Esunbulag_NaranbulagBag_sHanAltai | G36: 0 | I36: Ашиглалтанд шилжүүлж байна | J36: Говь-Алтай | K36: Есөнбулаг | L36: 3-р баг, Жаргалант | M36: Говь-Алтай аймаг, Есөнбулаг сум, Наранбулаг баг, Хан Алтай ресорс, Олборлолтын бүс | N36: Орон нутаг | O36: ROC_URC_GOA | P36: 46014 | Q36: D | T36: GOA_H4_sEsunbulagNaranbulagBagHanAltai-1 | V36: Mobicom | W36: battulga | X36: https://sm.mobicom.mn/mdobject/dataview/1525387912476&dv[id][]=17485411760722 | Y36: Бусад | Z36: 17485411760722 | AB36: 96.946591666666677156|46.107738888888889051
A37: 36 | B37: 17485410703742 | C37: Хэвийн | D37: 9 | E37: 251201-251231- 174841/1 | F37: Нэр олгоогүй | G37: 0 | I37: Хэвийн | J37: Улаанбаатар | K37: Хан-Уул | L37: 8-р хороо | W37: demberelsambuu | X37: https://sm.mobicom.mn/mdobject/dataview/1525387912476&dv[id][]=17485410703742
A38: 37 | B38: 17485410027462 | C38: Байгуулж байна | D38: 9 | E38: 11-T-81-00068 | F38: ZAV_Tosontsengel_TosonEnergy | G38: 0 | I38: Ашиглалтанд шилжүүлж байна | J38: Завхан | K38: Тосонцэнгэл | L38: 3-р баг, Улаантолгой | M38: Завхан аймаг Тосонцэнгэл сум 3-р баг Улаантолгой, Тосон Энержи | N38: Орон нутаг | O38: ROC_URC_ZAV | P38: 46017 | Q38: C | T38: ZAV_H4_TosontsengelTosonEnergy-1 ZAV_H4_TosontsengelTosonEnergy-2 | W38: sergelen.u | X38: https://sm.mobicom.mn/mdobject/dataview/1525387912476&dv[id][]=17485410027462 | Y38: Мобиком | Z38: 17485410027462 | AB38: 48.75394557198505,98.29093934650261
A39: 38 | B39: 17485408275042 | C39: Байгуулж байна | D39: 44 | E39: 11-T-41-00146 | F39: TUV_Zuunmod_1bag_MongolTuurgatanTeatr | G39: 0 | I39: Угсралт хийгдэж байна | J39: Төв | K39: Зуунмод | L39: 1-р баг, Номт | M39: Төв аймаг, Зуун мод сум, 1-р баг, Монгол туургатан театр-н дээвэр лүү гарах хэсгийн шатны тавцан дээр байрлалтай сайт. | N39: Аймгийн төв | O39: ID_Planning | P39: 46017 | Q39: B | S39: TUV_H3_TuvMongolTuurgatanTeatr-1 TUV_H3_TuvMongolTuurgatanTeatr-2 TUV_H3_TuvMongolTuurgatanTeatr-3 | T39: TUV_TuvMongolTuurgatanTeatr-1 TUV_TuvMongolTuurgatanTeatr-2 TUV_TuvMongolTuurgatanTeatr-3 TUV_H4_TuvMongolTuurgatanTeatr_B28-1 | W39: baterdene.tu | X39: https://sm.mobicom.mn/mdobject/dataview/1525387912476&dv[id][]=17485408275042 | Y39: Мобиком | Z39: 17485408275042 | AB39: 47.70541534956726,106.94250583648682
A40: 39 | B40: 17485406780672 | C40: Байгуулж байна | D40: 6 | E40: 11-T-62-00086 | F40: UVH_Ulziit_Guulinbag_HunOvoo | G40: 0 | I40: Хэрэгжилтд шилжүүлж байна | J40: Өвөрхангай | K40: Өлзийт | L40: Гуулин баг | M40: Өвөрхангай аймаг Өлзийт сум Гуулин баг Хүн овоо | N40: Орон нутаг | Q40: D | W40: erdenetsogt | X40: https://sm.mobicom.mn/mdobject/dataview/1525387912476&dv[id][]=17485406780672 | Y40: Мобиком | Z40: 17485406780672 | AB40: 46.54799,103.369338
A41: 40 | B41: 17485406551622 | C41: Хэвийн | D41: 49 | E41: 11-T-22-00055 | F41: SUH_Suhbaatar_5bag_TsairiinUurhai_Femto | G41: 0 | I41: Хэвийн | J41: Сүхбаатар | K41: Сүхбаатар | L41: 1-р баг, Баянгол | M41: Сүхбаатар аймаг Сүхбаатар сум 5-р баг Салхитын бор толгой Цайрын уурхай, Цайр баяжуулах үйлдвэр | N41: Орон нутаг | O41: ROC_URC_SUH | P41: 46008 | Q41: F | T41: SUH_B4_Femto_Polymetalresource-1 SUH_B4_Femto_Polymetalresource-2 | W41: Sainjargal | X41: https://sm.mobicom.mn/mdobject/dataview/1525387912476&dv[id][]=17485406551622 | Y41: Бусад | Z41: 17485406551622 | AB41: 46.82275,113.46713
A42: 41 | B42: 17485406462942 | C42: Байгуулж байна | D42: 6 | E42: 11-T-22-00054 | F42: SUH_Erdenetsagaan_BichigtiinBoomt_Mobi | G42: 0 | I42: Хэрэгжилтд шилжүүлж байна | J42: Сүхбаатар | K42: Эрдэнэцагаан | L42: 4-р баг, Хонгор | M42: Сүхбаатар аймаг, Эрдэнэцагаан сум, Бичигтийн боомт Моби толгой | N42: Орон нутаг | Q42: C | W42: erdenetsogt | X42: https://sm.mobicom.mn/mdobject/dataview/1525387912476&dv[id][]=17485406462942 | Y42: Мобиком | Z42: 17485406462942 | AB42: 45.77911,116.180044
A43: 42 | B43: 17485400517832 | C43: Байгуулж байна | D43: 5 | E43: 11-T-13-00249 | F43: ULN_BZD_39hor_Emart_Femto | G43: 0 | I43: Хэрэгжилтд шилжүүлж байна | J43: Улаанбаатар | K43: Баянзүрх | L43: 42-р хороо | N43: Улаанбаатар | Q43: D | T43: UB_B4_Femto_TengerPlazaEmart | W43: bilguun.baterdene | X43: https://sm.mobicom.mn/mdobject/dataview/1525387912476&dv[id][]=17485400517832 | Z43: 17485400517832 | AB43: 47.91295672880625,106.97834239999999
A44: 43 | B44: 17485398531602 | C44: Хэвийн | D44: 19 | E44: 11-T-83-00078 | F44: BAU_Deluun_3bag_TsagaanChuluutUul | G44: 0 | H44: 46027.095 | I44: Хэвийн | J44: Баян-Өлгий | K44: Дэлүүн | L44: 3-р баг, Хар уул | M44: Баян-Өлгий аймаг Дэлүүн сумаас зүүн хойд зүг 34км-д байрлах Хар уул багийн Цагаанчулуут уул | N44: Орон нутаг | O44: ROC_URC_BAU | P44: 46021 | Q44: F | T44: BAU_H4_Deluun3BagTsagaanChuluutUul_B8-1 BAU_H4_Deluun3BagTsagaanChuluutUul_B8-2 | V44: Netco | W44: battulga | X44: https://sm.mobicom.mn/mdobject/dataview/1525387912476&dv[id][]=17485398531602 | Y44: МХС | Z44: 17485398531602 | AB44: 90.616683333333327255|48.096741666666666504
A45: 44 | B45: 17485398287192 | C45: Хэвийн | D45: 44 | E45: 11-T-21-00081 | F45: DOR_Halhgol_HiliinTsergiin0189Angi_Femto | G45: 0 | I45: Хэвийн | J45: Дорнод | K45: Халхгол | L45: 1-р баг, Сүмбэр | M45: Дорнод Халх гол сум Хилийн цэрэг 0189дугаар салбар. | N45: Орон нутаг | O45: ROC_URC_DOR | P45: 46008 | Q45: D | T45: DOR_B4_Femto_HalhgolHiliinTsereg0189_B8-1 DOR_B4_Femto_HalhgolHiliinTsereg0189_B8-2 | W45: Sainjargal | X45: https://sm.mobicom.mn/mdobject/dataview/1525387912476&dv[id][]=17485398287192 | Y45: Бусад | Z45: 17485398287192 | AB45: 46.681888,119.276347
A46: 45 | B46: 17485398210632 | C46: Байгуулж байна | D46: 24 | E46: 11-T-84-00084 | F46: HOV_Altai_Holboo | G46: 0 | I46: Угсралт хийгдэж байна | J46: Ховд | K46: Алтай | L46: 4-р баг, Тахилт | M46: Ховд аймаг Алтай сум Холбоо | N46: Орон нутаг | O46: ROC_URC_HOV | Q46: A | V46: Mobicom | W46: battulga | X46: https://sm.mobicom.mn/mdobject/dataview/1525387912476&dv[id][]=17485398210632 | Y46: МХС | Z46: 17485398210632 | AB46: 92.52120833333333394|46.017783333333333928
A47: 46 | B47: 17485396463292 | C47: Хэвийн | D47: 5 | E47: 11-T-13-00248 | F47: ULN_BZD_11hor_MonteGardenClubHouse | G47: 0 | I47: Хэвийн | J47: Улаанбаатар | K47: Баянзүрх | L47: 2-р хороо | M47: БЗД, 2-р хороо Чулуутын аманд байрлах Монте Гарден хотхон. | N47: Улаанбаатар | O47: ID_Planning | P47: 46014 | Q47: C | T47: UB_H4_BZD11horMonteGardenClubHouse-1 UB_H4_BZD11horMonteGardenClubHouse-2 | W47: ankhbayar.g | X47: https://sm.mobicom.mn/mdobject/dataview/1525387912476&dv[id][]=17485396463292 | Y47: Мобиком | Z47: 17485396463292 | AB47: 47.85201790244141,107.07732439041138
A48: 47 | B48: 17485394808542 | C48: Хэвийн | D48: 44 | E48: 11-T-21-00080 | F48: DOR_Halhgol_HiliinTsergiin0105angi_Femto | G48: 0 | I48: Хэвийн | J48: Дорнод | K48: Халхгол | L48: 1-р баг, Сүмбэр | M48: Дорнод Халх гол сум Хилийн цэрэг 0105дугаар салбар | N48: Орон нутаг | O48: ROC_URC_DOR | P48: 46008 | Q48: D | T48: DOR_B4_Femto_HalhgolHiliinTsereg0105_B8-1 DOR_B4_Femto_HalhgolHiliinTsereg0105_B8-2 | W48: tsamba | X48: https://sm.mobicom.mn/mdobject/dataview/1525387912476&dv[id][]=17485394808542 | Y48: Бусад | Z48: 17485394808542 | AB48: 46.761711,118.242234
A49: 48 | B49: 17485393930282 | C49: Байгуулж байна | D49: 25 | E49: 11-T-14-00275 | F49: ULN_SBD_3hor_EncantoCentro_A3Block | G49: 0 | I49: Хэрэгжилтд шилжүүлж байна | J49: Улаанбаатар | K49: Сүхбаатар | L49: 3-р хороо | M49: Улаанбаатар хот Сүхбаатар хот 3-р хороо Eнканто центер A3 болок | N49: Улаанбаатар | O49: ID_Planning | P49: 46007 | Q49: C | T49: UB_H4_SBD3horEncantoCentroA3Block-1 UB_H4_SBD3horEncantoCentroA3Block-2 UB_H4_SBD3horEncantoCentroA3Block-3 UB_H4_iSBD3horEncantoCentroA3Block_B1-4 | W49: shiirevvaanchig | X49: https://sm.mobicom.mn/mdobject/dataview/1525387912476&dv[id][]=17485393930282 | Y49: Мобиком | Z49: 17485393930282 | AB49: 47.909305,106.904422
A50: 49 | B50: 17485385204822 | C50: Хэвийн | D50: 5 | E50: 11-T-18-00177 | F50: ULN_SHD_32hor_Tuul16-1Toot_Femto | G50: 0 | H50: 46001.034 | I50: Хэвийн | J50: Улаанбаатар | K50: Сонгинохайрхан | L50: 32-р хороо | M50: 22 tovchoo Urban tower LLC гаалийн агуулах. | N50: Улаанбаатар | O50: ID_System | P50: 46008 | Q50: F | T50: UB_B4_Femto_BridgeWarehouse-1 UB_B4_Femto_BridgeWarehouse-2 | W50: bilguun.baterdene | X50: https://sm.mobicom.mn/mdobject/dataview/1525387912476&dv[id][]=17485385204822 | Y50: Мобиком | Z50: 17485385204822 | AB50: 47.894123,106.709985
A51: 50 | B51: 17485385038382 | C51: Байгуулж байна | D51: 8 | E51: 11-T-13-00246 | F51: ULN_BZD_41hor_OneFamily59aBair | G51: 0 | I51: Хэрэгжилтд шилжүүлж байна | J51: Улаанбаатар | K51: Баянзүрх | M51: Улаанбаатар хот Баянзүрх дүүрэг 41-р хороо One Family Хотхон 59а байр | N51: Улаанбаатар | O51: ID_Planning | P51: 46000 | Q51: B | T51: UB_H4_BZD41horOneFamily59aBair-1 UB_H4_BZD41horOneFamily59aBair-2 UB_H4_BZD41horOneFamily59aBair-3 | W51: sergelen.u | X51: https://sm.mobicom.mn/mdobject/dataview/1525387912476&dv[id][]=17485385038382 | Y51: Мобиком | Z51: 17485385038382 | AB51: 47.92241998600973,106.95548179310211
A52: 51 | B52: 17485384808212 | C52: Хэвийн | D52: 9 | E52: 11-T-18-00176 | F52: ULN_SHD_29hor_Orgil21Tuv_iSector | G52: 0 | H52: 46009.013 | I52: Хэвийн | J52: Улаанбаатар | K52: Сонгинохайрхан | L52: 29-р хороо | M52: Улаанбаатар хот Сонгинохайхан дүүрэг 29-р хороо Оргил21 худалдааны төв Indoor | N52: Улаанбаатар | O52: ID_System | P52: 46007 | Q52: C | T52: UB_H4_isSHD29horOrgil21HudaldaaniiTuv-4 /Main: UB_BoldTower/ | W52: erdenetsogt | X52: https://sm.mobicom.mn/mdobject/dataview/1525387912476&dv[id][]=17485384808212 | Y52: Indoor Цамхаг байхгүй | Z52: 17485384808212 | AB52: 47.912375,106.819608
A53: 52 | B53: 17485384529282 | C53: Байгуулж байна | D53: 9 | E53: 11-T-43-00116 | F53: SEL_Altanbulag_3bag_BumanHangai | G53: 0 | I53: Хэрэгжилтд шилжүүлж байна | J53: Сэлэнгэ | K53: Алтанбулаг | L53: 3-р баг, Цөх | M53: Сэлэнгэ аймаг Алтанбулаг сум 3р баг Буман Хангай | N53: Орон нутаг | O53: ROC_DRC | Q53: B | W53: erdenetsogt | X53: https://sm.mobicom.mn/mdobject/dataview/1525387912476&dv[id][]=17485384529282 | Y53: Мобиком | Z53: 17485384529282 | AB53: 50.223777,106.279373
A54: 53 | B54: 17485371793632 | C54: Байгуулж байна | D54: 15 | E54: 11-T-48-00052 | F54: DUG_Mandalgovi_GreenGobiGarden_404_1Bair | G54: 0 | I54: СДБ-н ажил гүйцэтгэж байна | J54: Дундговь | K54: Сайнцагаан | L54: 7-р баг, Нарлаг | M54: Дундговь аймаг Мандалговь, Сайнцагаан сум, 7-р Нарлаг баг, Грийн Говь Гарден 405/1 байр | N54: Аймгийн төв | O54: ROC_GRC_DUG | Q54: B | S54: DUG_A3_TuvGreenGobiGarden404-1Bair-1 DUG_A3_TuvGreenGobiGarden404-1Bair-2 DUG_A3_TuvGreenGobiGarden404-1Bair-3 | T54: DUG_H4_TuvGreenGobiGarden404-1Bair-1 DUG_H4_TuvGreenGobiGarden404-1Bair-2 DUG_H4_TuvGreenGobiGarden404-1Bair-3 DUG_H4_TuvGreenGobiGarden404-1Bair_B7-1 DUG_H4_TuvGreenGobiGarden404-1Bair_B7-2 DUG_H4_TuvGreenGobiGarden404-1Bair_B7-3 DUG_H4_TuvGreenGobiGarden404-1Bair_B1-3 DUG_H4_TuvGreenGobiGarden404-1Bair_B28-3 | W54: nasanjargal.g | X54: https://sm.mobicom.mn/mdobject/dataview/1525387912476&dv[id][]=17485371793632 | Y54: Мобиком | Z54: 17485371793632 | AB54: 45.752888,106.268307
A55: 54 | B55: 17485371187772 | C55: Байгуулж байна | D55: 10 | E55: 11-T-18-00175 | F55: ULN_SHD_22hor_Tahilt356aToot_Unitel | G55: 0 | H55: 46105.305 | I55: СДБ-н ажил гүйцэтгэж байна | J55: Улаанбаатар | K55: Сонгинохайрхан | L55: 22-р хороо | M55: УБ хот, СХД 22-р хороо Тахилтын эцэс 356а тоот Юнител | N55: Улаанбаатар | O55: ID_System | Q55: B | T55: UB_H4_SHD22horTahilt356aTootUnitel-1 UB_H4_SHD22horTahilt356aTootUnitel-2 UB_H4_SHD22horTahilt356aTootUnitel-3 UB_H4_SHD22horTahilt356aTootUnitel_B7-2 | W55: erdenetsogt | X55: https://sm.mobicom.mn/mdobject/dataview/1525387912476&dv[id][]=17485371187772 | Y55: Юнител | Z55: 17485371187772 | AB55: 47.945285,106.672801
A56: 55 | B56: 17485364862962 | C56: Байгуулж байна | D56: 47 | E56: 11-T-42-00016 | F56: GOS_Sumber_2bag_Uulzvariin1-121_Unitel | G56: 0 | I56: Хэрэгжилтд шилжүүлж байна | J56: Говьсүмбэр | K56: Сүмбэр | L56: 2-р баг | M56: Говь-Сүмбэр аймгийн төв, 2-р баг, Уулзварын 1-121тоот хашаанд байршилтай. | N56: Аймгийн төв | O56: ROC_GRC_DOG | P56: 45986 | Q56: B | T56: GOS_H4_Tuv2BagUulzvariin1-121-1 GOS_H4_Tuv2BagUulzvariin1-121-2 GOS_H4_Tuv2BagUulzvariin1-121-3 | W56: baterdene.tu | X56: https://sm.mobicom.mn/mdobject/dataview/1525387912476&dv[id][]=17485364862962 | Y56: Юнител | Z56: 17485364862962 | AB56: 46.36264398,108.3711089
A57: 56 | B57: 17485364313512 | C57: Хэвийн | D57: 28 | E57: 11-T-63-00077 | F57: BUL_Teshig_DalanBag_DulaanHaanUul | G57: 0 | H57: 46109.038 | I57: Хэвийн | J57: Булган | K57: Тэшиг | L57: 3-р баг, Далан | M57: Булган аймаг Тэшиг сум Даланбаг ДулаанХаан уул | N57: Орон нутаг | O57: ROC_ERC | P57: 46108 | Q57: D | R57: BUL_H2_TeshigDalanBagDulaanHaanUul-1 BUL_H2_TeshigDalanBagDulaanHaanUul-2 | T57: BUL_H4_TeshigDalanBagDulaanHaanUul_B8-1 BUL_H4_TeshigDalanBagDulaanHaanUul_B8-2 | V57: Mobicom | W57: battulga | X57: https://sm.mobicom.mn/mdobject/dataview/1525387912476&dv[id][]=17485364313512 | Y57: Мобиком | Z57: 17485364313512 | AB57: 102.49884444444444398|49.827741666666668152
A58: 57 | B58: 17485360693802 | C58: Хэвийн | D58: 18 | E58: 11-T-41-00147 | F58: TUV_Bayanjargalan_BuuruljuutPowerPlant | G58: 0 | I58: Хэвийн | J58: Төв | K58: Баянжаргалан | L58: 1-р баг, Жаргалант | M58: Төв аймаг Баянжаргалан сум Бөөрөлжүүтийн цахилгаан станц Sinosteel LLC түрээсийн байр | N58: Орон нутаг | O58: ID_Planning | P58: 45988 | Q58: C | T58: TUV_H4_BayanjargalanBuuruljuutPowerPlant-1 TUV_H4_BayanjargalanBuuruljuutPowerPlant-2 TUV_H4_BayanjargalanBuuruljuutPowerPlant-3 | V58: Sinosteel LLC | W58: battulga | X58: https://sm.mobicom.mn/mdobject/dataview/1525387912476&dv[id][]=17485360693802 | Y58: Бусад | Z58: 17485360693802 | AB58: 107.88455555555556487|47.273299999999998988
A59: 58 | B59: 17485359265262 | C59: Байгуулж байна | D59: 20 | E59: 11-T-82-00069 | F59: GOA_Taishir_HurimtBag_ShohoinUildver | G59: 0 | H59: 46055.066 | I59: Ашиглалтанд шилжүүлж байна | J59: Говь-Алтай | K59: Тайшир | L59: 3-р баг, Далан | M59: Говь-Алтай аймаг Тайшир сум, Хуримт баг, Дөрвөлжин Тайшир шохойн үйлдвэр | N59: Орон нутаг | O59: ROC_URC_GOA | P59: 45988 | Q59: D | T59: GOA_H4_TaishirHurimtBagShohoinUildver_B8-1 GOA_H4_TaishirHurimtBagShohoinUildver_B8-2 | V59: дөрвөлжин Тайшир шохойн үйлдвэр | W59: battulga | X59: https://sm.mobicom.mn/mdobject/dataview/1525387912476&dv[id][]=17485359265262 | Y59: Бусад | Z59: 17485359265262 | AB59: 96.490102777777778442|46.656380555555557521
A60: 59 | B60: 17485357761892 | C60: Байгуулж байна | D60: 20 | E60: 11-T-61-00099 | F60: ORH_BayanUndur_BayanTsagaanBag_31Gudam | G60: 0 | I60: Ашиглалтанд шилжүүлж байна | J60: Орхон | K60: Баян-Өндөр | L60: 13-р баг, Баянцагаан | M60: Орхон аймаг Баян-Өндөр сум Баянцагаан баг 31-р гудамж | N60: Аймгийн төв | O60: ROC_ERC | P60: 45986 | Q60: B | T60: ERD_H4_BayantsagaanBag31Gudam-1 ERD_H4_BayantsagaanBag31Gudam-2 ERD_H4_BayantsagaanBag31Gudam-3 | W60: chinbayar.ch | X60: https://sm.mobicom.mn/mdobject/dataview/1525387912476&dv[id][]=17485357761892 | Y60: Мобиком | Z60: 17485357761892 | AB60: 49.04844504907864,104.09557700157166
A61: 60 | B61: 17485357736662 | C61: Байгуулж байна | D61: 28 | E61: 11-T-61-00097 | F61: ORH_BayanUndur_GovilBag_BayantsagaanOvoo | G61: 0 | I61: Шийдэл тодорхойлж байна | J61: Орхон | K61: Баян-Өндөр | L61: 14-р баг, Говил | M61: Баянцагаан овооны баруун талд | N61: Аймгийн төв | O61: ROC_ERC | P61: 45986 | Q61: C | T61: ERD_H4_GovilBayantsagaanOvoo-1 ERD_H4_GovilBayantsagaanOvoo-2 ERD_H4_GovilBayantsagaanOvoo-3 | W61: chinbayar.ch | X61: https://sm.mobicom.mn/mdobject/dataview/1525387912476&dv[id][]=17485357736662 | Y61: Мобиком | Z61: 17485357736662 | AB61: 49.112028985011634,104.043048620224
A62: 61 | B62: 17485354187352 | C62: Байгуулж байна | D62: 7 | E62: 11-T-46-00179 | F62: UMG_Tsogttsetsii_BayanburdHothon | G62: 0 | I62: Угсралт хийгдэж байна | J62: Өмнөговь | K62: Цогтцэций | L62: 3-р баг | M62: Өмнөговь аймаг Цогтцэций сум, Баянбүрд хотхон 512 тоот байр | N62: Орон нутаг | O62: ROC_GRC_UMG | P62: 45988 | Q62: C | T62: UMG_H4_TsogttsetsiiBayanburdHothon-1 UMG_H4_TsogttsetsiiBayanburdHothon-2 UMG_H4_TsogttsetsiiBayanburdHothon-3 | W62: ankhbayar.g | X62: https://sm.mobicom.mn/mdobject/dataview/1525387912476&dv[id][]=17485354187352 | Y62: Мобиком | Z62: 17485354187352 | AB62: 43.726801,105.566646
A63: 62 | B63: 17485349243752 | C63: Байгуулж байна | D63: 16 | E63: 11-T-17-00286 | F63: ULN_HUD_8hor_iMMSGreenBuilding | G63: 0 | I63: Хэрэгжилтд шилжүүлж байна | J63: Улаанбаатар | K63: Хан-Уул | L63: 8-р хороо | M63: Улаанбаатар хот Хан Уул дүүрэг 8-р хороо MMSGreenBuilding | N63: Улаанбаатар | O63: ID_System | P63: 45988 | Q63: C | T63: UB_H4_iHUD8horMMSGreenBuilding_B1-1 | V63: Mobicom | W63: battulga | X63: https://sm.mobicom.mn/mdobject/dataview/1525387912476&dv[id][]=17485349243752 | Y63: Indoor Цамхаг байхгүй | Z63: 17485349243752 | AB63: 106.78985833333332778|47.853311111111111131
A64: 63 | B64: 17485347311722 | C64: Хэвийн | D64: 11 | E64: 11-T-44-00092 | F64: DOG_ZamiinUud_UBTZ_Kass | G64: 0 | I64: Хэвийн | J64: Дорноговь | K64: Замын-Үүд | L64: 1-р баг | M64: Дорноговь аймаг Замын-Үүд сум төмөр замын билетийн касс | N64: Орон нутаг | O64: ROC_GRC_DOG | P64: 45973 | Q64: B | T64: DOG_H4_ZamUudUBTZKass-1 DOG_H4_ZamUudUBTZKass-2 DOG_H4_ZamUudUBTZKass-3 DOG_H4_ZamUudUBTZKass_B7-1 DOG_H4_ZamUudUBTZKass_B7-2 DOG_H4_ZamUudUBTZKass_B7-3 | W64: nasanjargal.g | X64: https://sm.mobicom.mn/mdobject/dataview/1525387912476&dv[id][]=17485347311722 | Y64: Мобиком | Z64: 17485347311722 | AB64: 43.71905520481687,111.90701723098755
A65: 64 | B65: 17485346143022 | C65: Хэвийн | D65: 14 | E65: 11-T-67-00099 | F65: HUV_Bayanzurh_AgarBag_SharGozgorUul | G65: 0 | I65: Хэвийн | J65: Хөвсгөл | K65: Баянзүрх | L65: 4-р баг, Агар | M65: Хөвсгөл аймаг Баянзүрх сум Агар баг Шар Гозор уул | N65: Орон нутаг | O65: ROC_ERC_HUV | P65: 45974 | Q65: F | R65: HUV_H2_BayanzurhAgarBagSharGozgorUul-1 HUV_H2_BayanzurhAgarBagSharGozgorUul-2 | T65: HUV_H4_BayanzurhAgarBagSharGozgorUul_B8-1 HUV_H4_BayanzurhAgarBagSharGozgorUul_B8-2 HUV_H4_BayanzurhAgarBagSharGozgorUul_B28-1 HUV_H4_BayanzurhAgarBagSharGozgorUul_B28-2 | W65: sergelen.u | X65: https://sm.mobicom.mn/mdobject/dataview/1525387912476&dv[id][]=17485346143022 | Y65: Мобиком | Z65: 17485346143022 | AB65: 50.091758,98.635445
A66: 65 | B66: 17485346142952 | C66: Байгуулж байна | D66: 6 | E66: 251110-251128- 195829/1 | F66: Нэр олгоогүй | G66: 0 | I66: Ашиглалтанд шилжүүлж байна | J66: Завхан | K66: Баянтэс | L66: 1-р баг, Бужир | W66: sergelen.u | X66: https://sm.mobicom.mn/mdobject/dataview/1525387912476&dv[id][]=17485346142952
A67: 66 | B67: 17485337354202 | C67: Хэвийн | D67: 12 | E67: 11-T-23-00077 | F67: HEN_BorUndur_3bag_BumbatGovi_500Toot | G67: 0 | H67: 46010.326 | I67: Хэвийн | J67: Хэнтий | K67: Бор-Өндөр | L67: 3-р баг, Бумбат | M67: Хэнтий аймаг Бор-Өндөр сум 3-р баг Бумбат говь 5-р гудамж 500 тоот | N67: Орон нутаг | O67: ROC_URC_HEN | P67: 45988 | Q67: B | T67: HEN_H4_BorUndur3bagBumbatGovi500Toot-1 HEN_H4_BorUndur3bagBumbatGovi500Toot-2 HEN_H4_BorUndur3bagBumbatGovi500Toot-3 | W67: erdenetsogt | X67: https://sm.mobicom.mn/mdobject/dataview/1525387912476&dv[id][]=17485337354202 | Y67: Мобиком | Z67: 17485337354202 | AB67: 46.257207,109.411719
A68: 67 | B68: 17485337327802 | C68: Хэвийн | D68: 13 | E68: 11-T-62-00087 | F68: UVH_Arvaiheer_12Bag_27Gudamj_2700Toot | G68: 0 | H68: 46003.331 | I68: Хэвийн | J68: Өвөрхангай | K68: Арвайхээр | L68: 12-р баг, Зүлэг жаргалант | M68: Өвөрхангай аймгийн Арвайхээр сумын 12-р баг, Зүлэгт жаргалант 27 гудамж 2700 тоот | N68: Аймгийн төв | O68: ROC_URC_UVH | P68: 46003 | Q68: C | T68: UBH_H4_Tuv12Bag27Gudamj2700Toot-1 UBH_H4_Tuv12Bag27Gudamj2700Toot-2 UBH_H4_Tuv12Bag27Gudamj2700Toot-3 | W68: erdenetsogt | X68: https://sm.mobicom.mn/mdobject/dataview/1525387912476&dv[id][]=17485337327802 | Y68: Мобиком | Z68: 17485337327802 | AB68: 46.248476,102.78348
A69: 68 | B69: 17485337306222 | C69: Хэвийн | D69: 10 | E69: 11-T-62-00084 | F69: UVH_Bayangol_TsaviinIherBag_ZuunHoimor | G69: 0 | H69: 46003.024 | I69: Хэвийн | J69: Өвөрхангай | K69: Баянгол | L69: Цавын ихэр баг | M69: Өвөрхангай аймаг Баянгол сум Цавын ихэр баг Зүүн хоймор | N69: Орон нутаг | O69: ROC_URC_UVH | P69: 46000 | Q69: F | R69: UBH_H2_BayangolTsaviinIherBagZuunHoimor-1 UBH_H2_BayangolTsaviinIherBagZuunHoimor-2 | T69: UBH_H4_BayangolTsaviinIherBagZuunHoimor_B8-1 UBH_H4_BayangolTsaviinIherBagZuunHoimor_B8-2 | W69: erdenetsogt | X69: https://sm.mobicom.mn/mdobject/dataview/1525387912476&dv[id][]=17485337306222 | Y69: Мобиком | Z69: 17485337306222 | AB69: 45.466527,103.489784
A70: 69 | B70: 17485337022242 | C70: Байгуулж байна | D70: 47 | E70: 11-T-64-00060 | F70: BAH_Ulziit_EliinAmBag_UndurHarUul | G70: 0 | I70: Хэрэгжилтд шилжүүлж байна | J70: Баянхонгор | K70: Өлзийт | L70: 3-р баг, Ёлын ам | M70: Баянхонгор аймаг, Өлзийт сум, Ёлийн ам багийн Өндөрхар уулан дээр байршилтай. Аймгийн төвөөс 60км зайтай | N70: Орон нутаг | O70: ROC_URC_BAH | P70: 45986 | Q70: F | R70: BAH_H2_UlziitEliinAmBagUndurHarUul-1 BAH_H2_UlziitEliinAmBagUndurHarUul-2 | T70: BAH_H4_UlziitEliinAmBagUndurHarUul_B8-1 BAH_H4_UlziitEliinAmBagUndurHarUul_B8-2 | W70: baterdene.tu | X70: https://sm.mobicom.mn/mdobject/dataview/1525387912476&dv[id][]=17485337022242 | Y70: Мобиком | Z70: 17485337022242 | AB70: 46.23185,101.169329
A71: 70 | B71: 17485335685762 | C71: Хэвийн | D71: 7 | E71: 11-T-13-00247 | F71: ULN_BZD_11hor_ZuunZalaatiinAm_Exsource | G71: 0 | H71: 45974.064 | I71: Хэвийн | J71: Улаанбаатар | K71: Баянзүрх | L71: 11-р хороо | M71: Улаанбаатар хот, Баянзүрх дүүрэг, 11-р хороо Зүүн залаатын ам, &quot;Эксорс&quot; ХХК оффиссийн барилгын дээвэрт 3м Onepole дээр суурилуулсан. | N71: Улаанбаатар | O71: ID_System | P71: 45972 | Q71: C | T71: UB_H4_BZD11horZuunZalaatiinAmExsource-1 UB_H4_BZD11horZuunZalaatiinAmExsource-2 | W71: erdenetsogt | X71: https://sm.mobicom.mn/mdobject/dataview/1525387912476&dv[id][]=17485335685762 | Y71: Мобиком | Z71: 17485335685762 | AB71: 47.88109,107.015843
A72: 71 | B72: 17485324738392 | C72: Хэвийн | D72: 15 | E72: 11-T-17-00289 | F72: ULN_HUD_6hor_YarmagTower | G72: 0 | I72: Хэвийн | J72: Улаанбаатар | K72: Хан-Уул | L72: 6-р хороо | M72: Улаанбаатар хот Хан-Уул дүүрэг 6р хороо Яармаг товер | N72: Улаанбаатар | O72: ID_System | P72: 45960 | Q72: C | T72: UB_H4_HUD6horYarmagTower-1 UB_H4_HUD6horYarmagTower-2 UB_H4_HUD6horYarmagTower-3 UB_H4_iHUD6horNominMakro-1 (Source site: UB_HUD6horYarmagTower ) | W72: nasanjargal.g | X72: https://sm.mobicom.mn/mdobject/dataview/1525387912476&dv[id][]=17485324738392 | Y72: Мобиком | Z72: 17485324738392 | AB72: 47.866107329266924,106.8107932806015
A73: 72 | B73: 17485322903882 | C73: Байгуулж байна | D73: 32 | E73: 11-T-17-00296 | F73: ULN_HUD_19hor_SilaCentre_iSector | G73: 0 | H73: 45958.068 | I73: Хэрэгжилтд шилжүүлж байна | J73: Улаанбаатар | K73: Хан-Уул | L73: 19-р хороо | M73: Улаанбаатар хот Хан уул дүүрэг 19-р хороо CarreFour ''Sila Centre'' Худалдааны төв TCB1-ээс 3 км -ын зайтай. | N73: Улаанбаатар | O73: ID_Planning | P73: 45960 | Q73: C | T73: ULN_H4_isHUD19horSilaCentre-1 /BBU ULN_HUD1horHivs / | W73: tsamba | X73: https://sm.mobicom.mn/mdobject/dataview/1525387912476&dv[id][]=17485322903882 | Y73: Indoor Цамхаг байхгүй | Z73: 17485322903882 | AB73: 47.89407752903225,106.90804544612028
A74: 73 | B74: 17485314025882 | C74: Байгуулж байна | D74: 17 | E74: 11-T-17-00287 | F74: ULN_HUD_4hor_NominHypermarket_iSector | G74: 0 | I74: Угсралт хийгдэж байна | J74: Улаанбаатар | K74: Хан-Уул | L74: 4-р хороо | M74: Улаанбаатар хот Хан уул дүүрэг 4-р хороо Номин Хапермаркет худалааны төвийн В#1 давхарт | N74: Улаанбаатар | O74: ID_System | P74: 45961 | Q74: C | T74: UB_H4_isHUD4horNominHyperMarket_B1-1 (Source site: UB_iHUD5horTitanCenter ) | V74: Mobicom | W74: battulga | X74: https://sm.mobicom.mn/mdobject/dataview/1525387912476&dv[id][]=17485314025882 | Y74: Бусад | Z74: 17485314025882 | AB74: 106.8379111111111115|47.874013888888889312
A75: 74 | B75: 17485312800012 | C75: Хэвийн | D75: 45 | E75: 11-T-61-00107 | F75: ORH_BayanUndur_1Surguuli_Sector | G75: 0 | I75: Хэвийн | J75: Орхон | K75: Баян-Өндөр | L75: 1-р баг, Зэст | M75: Эрдэнэт хот, Хүрэнбулаг үйлчилгээний төвийн урд 1-р дунд сургуулийн шинэ өргөтгөл байрны дээвэр дээр сектор сайт | N75: Аймгийн төв | O75: ROC_ERC | P75: 45958 | Q75: C | T75: ERD_H4_s1Surguuli-1 ERD_H4_s1Surguuli_B28-1 (EnodeB- ERD_3hor7bair) | W75: baterdene.tu | X75: https://sm.mobicom.mn/mdobject/dataview/1525387912476&dv[id][]=17485312800012 | Y75: Мобиком | Z75: 17485312800012 | AB75: 49.02864846940464,104.05483721399752
A76: 75 | B76: 17485312799952 | C76: Хэвийн | D76: 46 | E76: 11-T-13-00245 | F76: ULN_BZD_6hor_BayanzurhZah_IndoorSector | G76: 0 | I76: Хэвийн | J76: Улаанбаатар | K76: Баянзүрх | L76: 1-р хороо | M76: БЗД, 6-р хороо, Баянзүрх захын урд хаалгаар В1 давхарлуу ороод зүүн гар талд байрласан цахилгааны өрөөнд байрлалтай. TCB- байрнаас 2км зайтай. | N76: Улаанбаатар | O76: ID_Planning | P76: 45961 | Q76: C | T76: UB_H4_isBZD6horBayanzurhZah_B1-1 (enodeB - UB_SEZDS) | W76: baterdene.tu | X76: https://sm.mobicom.mn/mdobject/dataview/1525387912476&dv[id][]=17485312799952 | Y76: Indoor Цамхаг байхгүй | Z76: 17485312799952 | AB76: 47.9168046044488,106.93354618612318
A77: 76 | B77: 17485312798282 | C77: Хэвийн | D77: 46 | E77: 11-T-13-00244 | F77: ULN_BZD_37hor_SereneTown_86-1Bair | G77: 0 | I77: Хэвийн | J77: Улаанбаатар | K77: Баянзүрх | L77: 1-р хороо | M77: Улаанбаатар хот, Баянзүрх дүүрэг, 37-р хороо Цагдаагийн академи гудамж &quot;Серени таун&quot; хотхон 86/1-р байрны дээвэр дээр minishelter сайт TCB-1 байрнаас 10км-н зайтай. | N77: Улаанбаатар | O77: ID_Planning | P77: 45960 | Q77: B | T77: UB_H4_BZD37horSereneTown86-1Bair-1 UB_H4_BZD37horSereneTown86-1Bair-2 UB_H4_BZD37horSereneTown86-1Bair-3 UB_H4_BZD37horSereneTown86-1Bair_B7-2 | W77: baterdene.tu | X77: https://sm.mobicom.mn/mdobject/dataview/1525387912476&dv[id][]=17485312798282 | Y77: Мобиком | Z77: 17485312798282 | AB77: 47.909521,106.989071
A78: 77 | B78: 17485312798222 | C78: Хэвийн | D78: 45 | E78: 11-T-17-00294 | F78: ULN_HUD_14hor_BuhugTurgeniiAm_Unitel | G78: 0 | I78: Хэвийн | J78: Улаанбаатар | K78: Хан-Уул | L78: 1-р хороо | M78: ХУД, 14-р хороо, Бөхөг-Түргэний аманд байрласан уулан дээр Юнителийн сайтад түрээсээр орсон. | N78: Улаанбаатар | O78: ID_Planning | P78: 45960 | Q78: C | T78: UB_H4_HUD14horBuhugTurgeniiAmUnitel-1 UB_H4_HUD14horBuhugTurgeniiAmUnitel-2 UB_H4_HUD14horBuhugTurgeniiAmUnitel-3 | W78: baterdene.tu | X78: https://sm.mobicom.mn/mdobject/dataview/1525387912476&dv[id][]=17485312798222 | Y78: Юнител | Z78: 17485312798222 | AB78: 47.742891,106.819454
A79: 78 | B79: 17485312798162 | C79: Хэвийн | D79: 46 | E79: 11-T-13-00240 | F79: ULN_BZD_11hor_HonhorEruulMendTuv_Unitel | G79: 0 | I79: Хэвийн | J79: Улаанбаатар | K79: Баянзүрх | L79: 1-р хороо | M79: Баянзүрх дүүрэг 11-р хороо Хонхор тосгон Булгачин гудамж Хонхор тосгоны эрүүл мэндийн төвийн хашаанд Юнителийн хашаанд байрлалтай Minishelter-тэй сайт. Техникийн төв байрнаас 27км зайтай. | N79: Улаанбаатар | O79: ID_Planning | P79: 45953 | Q79: C | T79: UB_H4_BZD11horHonhorEruulMendTuvUnitel-1 UB_H4_BZD11horHonhorEruulMendTuvUnitel-2 UB_H4_BZD11horHonhorEruulMendTuvUnitel-3 UB_H4_BZD11horHonhorEruulMendTuvUnitel_B28-1 | W79: baterdene.tu | X79: https://sm.mobicom.mn/mdobject/dataview/1525387912476&dv[id][]=17485312798162 | Y79: Юнител | Z79: 17485312798162 | AB79: 47.811499652407285,107.1623543582194
A80: 79 | B80: 17485312566102 | C80: Байгуулж байна | D80: 12 | E80: 11-T-81-00065 | F80: ZAV_Bayantes_Bujirbag_BujiriinUrdOvgor | G80: 0 | I80: Хэрэгжилтд шилжүүлж байна | J80: Завхан | K80: Баянтэс | L80: 1-р баг, Бужир | M80: Завхан аймаг Баянтэс сум Бужир баг Бужирийн урд овгор уул | N80: Орон нутаг | O80: ROC_URC_ZAV | P80: 45986 | Q80: F | R80: ZAV_H2_BayantesBujirbagBujiriinUrdOvgor-1 ZAV_H2_BayantesBujirbagBujiriinUrdOvgor-2 | T80: ZAV_H4_BayantesBujirbagBujiriinUrdOvgor_B8-1 ZAV_H4_BayantesBujirbagBujiriinUrdOvgor_B8-2 | W80: sergelen.u | X80: https://sm.mobicom.mn/mdobject/dataview/1525387912476&dv[id][]=17485312566102 | Y80: Мобиком | Z80: 17485312566102 | AB80: 49.66269521165191,96.66433416612483
A81: 80 | B81: 17485311082812 | C81: Хэвийн | D81: 23 | E81: 11-T-18-00157 | F81: ULN_SHD_20hor_TolgoitUrtuuOffice | G81: 0 | I81: Хэвийн | J81: Улаанбаатар | K81: Сонгинохайрхан | L81: 20-р хороо | M81: Улаанбаатар хот Сонгинохайрхан дүүрэг 20-р хороо Толгойт өртөө оффисын гадаа гэрэлтүүлэгийн цамхаг | N81: Улаанбаатар | O81: ID_Planning | P81: 45961 | Q81: C | T81: UB_H4_SHD20horTolgoitUrtuuOffice-1 UB_H4_SHD20horTolgoitUrtuuOffice-2 UB_H4_SHD20horTolgoitUrtuuOffice-3 | V81: Mobicom | W81: battulga | X81: https://sm.mobicom.mn/mdobject/dataview/1525387912476&dv[id][]=17485311082812 | Y81: Бусад | Z81: 17485311082812 | AB81: 106.74730277777777587|47.904108333333333292
A82: 81 | B82: 17485310673002 | C82: Байгуулж байна | D82: 32 | E82: 11-T-18-00163 | F82: ULN_SHD_361Garam_HairthaanSaldag | G82: 0 | H82: 46105.285 | I82: Ашиглалтанд шилжүүлж байна | J82: Улаанбаатар | K82: Сонгинохайрхан | L82: 21-р хороо | M82: Улаанбаатар хот Сонгино Хайрхан дүүрэг 21-р хороо 361 гарам Хайртхаан салдаг | N82: Улаанбаатар | O82: ID_Planning | P82: 46041 | Q82: C | T82: UB_H4_SHD361GaramHairthaanSaldag-1 UB_H4_SHD361GaramHairthaanSaldag-2 UB_H4_SHD361GaramHairthaanSaldag-3 | V82: Mobicom | W82: battulga | X82: https://sm.mobicom.mn/mdobject/dataview/1525387912476&dv[id][]=17485310673002 | Y82: Мобиком | Z82: 17485310673002 | AB82: 106.51140833333333546|48.01512222222222448
A83: 82 | B83: 17485310604782 | C83: Байгуулж байна | D83: 18 | E83: 11-T-65-00073 | F83: ARH_Hairhan_Mogoibag_MunhiinShovgor | G83: 0 | I83: Угсралт хийгдэж байна | J83: Архангай | K83: Хайрхан | L83: 4-р баг, Могой | M83: Архангай аймаг Хайрхан сум 4-р баг Могой баг Мөнхийн шовгор | N83: Орон нутаг | O83: ROC_URC_ARH | P83: 45954 | Q83: F | R83: ARH_H2_HairhanMogoiBagMunhiinShovgor-1 ARH_H2_HairhanMogoiBagMunhiinShovgor-2 | T83: ARH_H4_HairhanMogoiBagMunhiinShovgor_B8-1 ARH_H4_HairhanMogoiBagMunhiinShovgor_B8-2 ARH_H4_HairhanMogoiBagMunhiinShovgor_B28-1 ARH_H4_HairhanMogoiBagMunhiinShovgor_B28-2 | W83: nasanjargal.g | X83: https://sm.mobicom.mn/mdobject/dataview/1525387912476&dv[id][]=17485310604782 | Y83: Мобиком | Z83: 17485310604782 | AB83: 48.639235,102.151982
A84: 83 | B84: 17485310604722 | C84: Байгуулж байна | D84: 18 | E84: 11-T-65-00072 | F84: ARH_Tsetserleg_Hongorjbag_TaliinHongorj | G84: 0 | I84: Угсралт хийгдэж байна | J84: Архангай | K84: Цэцэрлэг | L84: 4-р баг, Хонгорж | M84: Архангай аймаг Цэцэрлэг сум 4-р баг Хонгорж баг Талын хонгорж хайрхан | N84: Орон нутаг | O84: ROC_URC_ARH | P84: 45957 | Q84: F | R84: ARH_H2_TsetserlegHongorjBagTaliinHongorj-1 ARH_H2_TsetserlegHongorjBagTaliinHongorj-2 | T84: ARH_H4_TsetserlegHongorjBagTaliinHongorj_B8-1 ARH_H4_TsetserlegHongorjBagTaliinHongorj_B8-2 ARH_H4_TsetserlegHongorjBagTaliinHongorj_B28-1 ARH_H4_TsetserlegHongorjBagTaliinHongorj_B28-2 | W84: nasanjargal.g | X84: https://sm.mobicom.mn/mdobject/dataview/1525387912476&dv[id][]=17485310604722 | Y84: Мобиком | Z84: 17485310604722 | AB84: 47.91674471367652,106.9163167476654
A85: 84 | B85: 17485310604662 | C85: Байгуулж байна | D85: 28 | E85: 11-T-48-00045 | F85: DUG_Saintsagaan_TevshBag | G85: 0 | I85: Угсралт хийгдэж байна | J85: Дундговь | K85: Сайнцагаан | L85: 2-р баг, Тэвш | M85: Дундговь аймаг Сайнцагаан сум 2-р баг Тэвш баг | N85: Орон нутаг | O85: ROC_GRC_DUG | P85: 45961 | Q85: F | R85: DUG_H2_SaintsagaanTevshBag-1 DUG_H2_SaintsagaanTevshBag-2 | T85: DUG_H4_SaintsagaanTevshBag_B8-1 DUG_H4_SaintsagaanTevshBag_B8-2 | W85: nasanjargal.g | X85: https://sm.mobicom.mn/mdobject/dataview/1525387912476&dv[id][]=17485310604662 | Y85: Мобиком | Z85: 17485310604662 | AB85: 46.02742,106.068991
A86: 85 | B86: 17485310604602 | C86: Байгуулж байна | D86: 18 | E86: 11-T-48-00046 | F86: DUG_Saintsagaan_Naranbag | G86: 0 | I86: Угсралт хийгдэж байна | J86: Дундговь | K86: Сайнцагаан | L86: 1-р баг, Наран | M86: Дундговь аймаг Сайнцагаан сум 1-р баг Наран баг | N86: Орон нутаг | O86: ROC_GRC_DUG | P86: 45974 | Q86: F | R86: DUG_H2_SaintsagaanNaranBag-1 DUG_H2_SaintsagaanNaranBag-2 | T86: DUG_H4_SaintsagaanNaranBag_B8-1 DUG_H4_SaintsagaanNaranBag_B8-2 | V86: yu | W86: nasanjargal.g | X86: https://sm.mobicom.mn/mdobject/dataview/1525387912476&dv[id][]=17485310604602 | Y86: Мобиком | Z86: 17485310604602 | AB86: 47.91674471367652,106.9163167476654
A87: 86 | B87: 17485310353182 | C87: Хэвийн | D87: 11 | E87: 11-T-43-00115 | F87: DAR_Darhan_ShireeNuruuUrd_71Toot | G87: 0 | H87: 46014.113 | I87: Хэвийн | J87: Сэлэнгэ | K87: Сайхан | L87: 3-р баг, Номгон | M87: Сэлэнгэ аймаг Сайхан сум 3-р баг, Дарханы Ширээ нуруу урд 71 тоот хашаа (Газар зүйн нэршлээр Сэлэнгэ боловч байршлаар Дархан-д тул cell name-г ШирээНуруугаар үүсгэв) | N87: Орон нутаг | O87: ROC_DRC | P87: 46014 | Q87: C | T87: DAR_H4_ShireeNuruuUrd71Toot-1 DAR_H4_ShireeNuruuUrd71Toot-2 DAR_H4_ShireeNuruuUrd71Toot-3 | W87: erdenetsogt | X87: https://sm.mobicom.mn/mdobject/dataview/1525387912476&dv[id][]=17485310353182 | Y87: Мобиком | Z87: 17485310353182 | AB87: 49.47216,105.89017
A88: 87 | B88: 17485310304332 | C88: Хэвийн | D88: 16 | E88: 11-T-17-00292 | F88: ULN_HUD_5hor_TitanPlus_Sector | G88: 0 | I88: Хэвийн | J88: Улаанбаатар | K88: Хан-Уул | L88: 5-р хороо | M88: Улаанбаатар хот Хан-Уул дүүрэг 5-р хороо Titan Plus | N88: Улаанбаатар | O88: ID_System | P88: 45952 | Q88: C | T88: UB_H4_sHUD5horTitanPlus-3 (Source site: UB_iHUD5horTitanCenter) | V88: Mobicom | W88: battulga | X88: https://sm.mobicom.mn/mdobject/dataview/1525387912476&dv[id][]=17485310304332 | Y88: Мобиком | Z88: 17485310304332 | AB88: 106.82294999999999163|47.869552777777776953
A89: 88 | B89: 17485297941402 | C89: Хэвийн | D89: 14 | E89: 11-T-81-00062 | F89: ZAV_Ider_DarhanUulbag_BumbaniiIhOroiUul | G89: 0 | I89: Хэвийн | J89: Завхан | K89: Идэр | L89: Дархан-Уул | M89: Завхан аймаг Идэр сум Дархан-Уул баг Бумбаны Их Орой уул | N89: Орон нутаг | O89: ROC_URC_ZAV | P89: 45968 | Q89: F | R89: ZAV_H2_IderDarhanUulBagBumbaniiUul-1 ZAV_H2_IderDarhanUulBagBumbaniiUul-2 | T89: ZAV_H4_IderDarhanUulBagBumbaniiUul_B8-1 ZAV_H4_IderDarhanUulBagBumbaniiUul_B8-2 | W89: sergelen.u | X89: https://sm.mobicom.mn/mdobject/dataview/1525387912476&dv[id][]=17485297941402 | Y89: Мобиком | Z89: 17485297941402 | AB89: 48.045342,97.538137
A90: 89 | B90: 17485297941332 | C90: Хэвийн | D90: 14 | E90: 11-T-81-00063 | F90: ZAV_Ider_ManuustaiBag_ManuustaiUul | G90: 0 | I90: Хэвийн | J90: Завхан | K90: Идэр | L90: Мануустай | M90: Завхан аймаг Идэр сум Мануустай баг Мануустай уул | N90: Орон нутаг | O90: ROC_URC_ZAV | P90: 45958 | Q90: D | T90: ZAV_H4_IderManuustaiBagManuustaiUul_B8-1 ZAV_H4_IderManuustaiBagManuustaiUul_B8-2 ZAV_H4_IderManuustaiBagManuustaiUul_B28-1 ZAV_H4_IderManuustaiBagManuustaiUul_B28-2 | W90: sergelen.u | X90: https://sm.mobicom.mn/mdobject/dataview/1525387912476&dv[id][]=17485297941332 | Y90: Мобиком | Z90: 17485297941332 | AB90: 47.91674471367652,106.9163167476654
A91: 90 | B91: 17485297932212 | C91: Хэвийн | D91: 50 | E91: 11-T-61-00098 | F91: ORH_BayanUndur_TsagaanChuluutBag_35-1 | G91: 0 | I91: Хэвийн | J91: Орхон | K91: Баян-Өндөр | L91: 11-р баг, Цагаанчулуут | M91: 35р гудамж 1тоот айлын хашаанд | N91: Аймгийн төв | O91: ROC_ERC | P91: 45962 | Q91: B | T91: ERD_H4_TsagaanChuluutBag35_1-1 ERD_H4_TsagaanChuluutBag35_1-2 ERD_H4_TsagaanChuluutBag35_1-3 | W91: chinbayar.ch | X91: https://sm.mobicom.mn/mdobject/dataview/1525387912476&dv[id][]=17485297932212 | Y91: Мобиком | Z91: 17485297932212 | AB91: 49.0217447878187,104.02061060070992
A92: 91 | B92: 17485287085882 | C92: Хэвийн | D92: 47 | E92: 11-T-61-00104 | F92: ORH_BayanUndur_ErdenetHivs_Indoor | G92: 0 | I92: Хэвийн | J92: Орхон | K92: Баян-Өндөр | L92: 4-р баг, Хүрэнбулаг | M92: Орхон аймаг, Эрдэнэт хотын төвд Эрдэнэт Хивс үйлдвэрийн барилгын яг гол хавьцаа инженер техникийн албаны өрөөнд тоног төхөөрөмжөө байршуулж Indoor сүлжээ оруулсан. | N92: Аймгийн төв | O92: ROC_ERC | P92: 45961 | Q92: C | T92: ERD_H4_iErdenetHivs_B1-1F ERD_H4_iErdenetHivs_B1-2F | W92: baterdene.tu | X92: https://sm.mobicom.mn/mdobject/dataview/1525387912476&dv[id][]=17485287085882 | Y92: Indoor Цамхаг байхгүй | Z92: 17485287085882 | AB92: 49.035364,104.081656
A93: 92 | B93: 17485287085822 | C93: Хэвийн | D93: 46 | E93: 11-T-61-00102 | F93: ORH_BayanUndur_OrhonMall_Indoor | G93: 0 | I93: Хэвийн | J93: Орхон | K93: Баян-Өндөр | L93: 3-р баг, Уурхайчин | M93: Орхон аймаг, Баян-Өндөр сум, 8-р баг Orkhon mall их дэлгүүрийн 1 давхрын серверийн өрөөнд байршилтай. | N93: Аймгийн төв | O93: ROC_ERC | P93: 45940 | Q93: C | T93: ERD_H4_iOrhonMall_B1-1 ERD_H4_iOrhonMall_B1-2 | W93: baterdene.tu | X93: https://sm.mobicom.mn/mdobject/dataview/1525387912476&dv[id][]=17485287085822 | Y93: Indoor Цамхаг байхгүй | Z93: 17485287085822 | AB93: 49.030162,104.036146
A94: 93 | B94: 17485280415002 | C94: Хэвийн | D94: 28 | E94: 11-T-84-00082 | F94: HOV_Jargalant_3bag_AjUildveriinPark | G94: 0 | I94: Хэвийн | J94: Ховд | K94: Жаргалант | L94: 3-р баг, Бичигт | M94: Ховд аймаг Жаргалант сум 3-р баг Аж үйлдвэрийн парк | N94: Аймгийн төв | O94: ROC_URC_HOV | P94: 45952 | Q94: C | T94: HOV_H4_Tuv3BagAjUildveriinPark-1 HOV_H4_Tuv3BagAjUildveriinPark-2 HOV_H4_Tuv3BagAjUildveriinPark-3 | V94: Mobicom | W94: battulga | X94: https://sm.mobicom.mn/mdobject/dataview/1525387912476&dv[id][]=17485280415002 | Y94: Мобиком | Z94: 17485280415002 | AB94: 91.669700000000005957|47.990836111111114803
A95: 94 | B95: 17485277195832 | C95: Байгуулж байна | D95: 22 | E95: 11-T-63-00076 | F95: BUL_Saihan_ManuultBag_UlaanEnger | G95: 0 | I95: Шийдэл тодорхойлж байна | J95: Булган | K95: Сайхан | L95: 1-р баг, Мануулт | M95: Булган аймаг Сайхан сум 1-р баг Мануулт баг нарийн энгэр уул | N95: Орон нутаг | O95: ROC_ERC | P95: 45952 | Q95: F | R95: BUL_H2_SaihanManuultBagUlaanEnger-1 BUL_H2_SaihanManuultBagUlaanEnger-2 | T95: BUL_H4_SaihanManuultBagUlaanEnger_B8-1 BUL_H4_SaihanManuultBagUlaanEnger_B8-2 BUL_H4_SaihanManuultBagUlaanEnger_B28-1 BUL_H4_SaihanManuultBagUlaanEnger_B28-2 | V95: Mobicom | W95: battulga | X95: https://sm.mobicom.mn/mdobject/dataview/1525387912476&dv[id][]=17485277195832 | Y95: Мобиком | Z95: 17485277195832 | AB95: 102.47680277777777746|48.319830555555562057
A96: 95 | B96: 17485275896632 | C96: Хэвийн | D96: 10 | E96: 11-T-81-00067 | F96: ZAV_Uliastai_ChigesteiBag_300BBair | G96: 0 | I96: Хэвийн | J96: Завхан | K96: Улиастай | L96: 2-р баг, Жаргалант | M96: Завхан аймаг, Улиастай хот, Чигэстэй 2-р баг, 300В байр | N96: Аймгийн төв | O96: ROC_URC_ZAV | P96: 45960 | Q96: B | T96: ZAV_H4_TuvChigesteiBag300bBair-1 ZAV_H4_TuvChigesteiBag300bBair-2 ZAV_H4_TuvChigesteiBag300bBair-3 | W96: ankhbayar.g | X96: https://sm.mobicom.mn/mdobject/dataview/1525387912476&dv[id][]=17485275896632 | Y96: Мобиком | Z96: 17485275896632 | AB96: 47.737712,96.85188
A97: 96 | B97: 17485273973922 | C97: Байгуулж байна | D97: 1 | E97: 11-T-84-00083 | F97: HOV_Jargalant_IhBuyanZah_Femto | G97: 0 | I97: Хэрэгжилтд шилжүүлж байна | J97: Ховд | K97: Жаргалант | L97: 1-р баг, Алагтолгой | M97: Их буян худалдааны төв | N97: Орон нутаг | O97: ROC_URC_HOV | P97: 45649 | Q97: F | T97: HOV_B4_Femto_Jargalant_Ikhbuyanzah | W97: smadmin1 | X97: https://sm.mobicom.mn/mdobject/dataview/1525387912476&dv[id][]=17485273973922 | Y97: Мобиком | Z97: 17485273973932 | AB97: 91.64707/48.00118
A98: 97 | B98: 17485273973852 | C98: Хэвийн | E98: 11-T-61-00105 | F98: ORH_BayanUndur_1microMaestro_femto | G98: 0 | I98: Хэвийн | J98: Орхон | K98: Баян-Өндөр | L98: 1-р баг, Зэст | M98: 1-р микро уурхайчин Maestro Restaurant | N98: Орон нутаг | O98: ROC_ERC | P98: 45821 | Q98: F | T98: ERD_B4_Femto_Mayestro-1 ERD_B4_Femto_Mayestro-2 | W98: smadmin1 | X98: https://sm.mobicom.mn/mdobject/dataview/1525387912476&dv[id][]=17485273973852 | Y98: Мобиком | Z98: 17485273973862 | AB98: 104.05902/49.03235
A99: 98 | B99: 17485273973782 | C99: Буусан | D99: 1 | E99: 11-T-81-00061 | F99: Zav_Tosontsengel_TosonEnergy_Femto | G99: 0 | I99: Буусан | J99: Завхан | K99: Тосонцэнгэл | L99: 4-р баг, Рашаант | M99: Тосон энержи Дулааны цахилгаан станц | N99: Орон нутаг | O99: ROC_URC_ZAV | P99: 45649 | W99: smadmin1 | X99: https://sm.mobicom.mn/mdobject/dataview/1525387912476&dv[id][]=17485273973782 | Y99: Мобиком | Z99: 17485273973792 | AB99: 98.260531/48.7627151
A100: 99 | B100: 17485273973712 | C100: Хэвийн | E100: 11-T-63-00078 | F100: BUL_Rashaant_MarsTsainiiGazar_Femto | G100: 0 | I100: Хэвийн | J100: Булган | K100: Рашаант | L100: 1-р баг, Хөгнө хан | M100: Mars цайны газар | N100: Орон нутаг | O100: ID_Planning | Q100: F | T100: BUL_B4_Femto_RashaantMars | W100: smadmin1 | X100: https://sm.mobicom.mn/mdobject/dataview/1525387912476&dv[id][]=17485273973712 | Y100: Мобиком | Z100: 17485273973722 | AB100: 104.186143/47.356171
...
